Workbook

Sheet Mode d'emploi
A1: HEAT — Catalogue des leviers, version 3
A2: Régénéré depuis le code du jeu le 26/08/2026 — jeu en version v0.9.1.
A4: Ce que contient ce fichier
A5: Onglet Catalogue — les leviers réellement jouables, extraits automatiquement du fichier du jeu. Coûts, seuils, latences,
A6: époques, prérequis, probabilités, contre-leviers et combinaisons sont les valeurs du moteur, pas des estimations.
A7: Onglet Non retenus — les leviers du catalogue d'août jamais construits, chacun avec le verdict qui l'écarte.
A8: Onglet Correspondance — les identifiants qui ne désignent pas le même levier dans le catalogue d'août et dans le jeu.
A9: Onglet Contrôles — répartitions et cohérence des contre-leviers, recalculées par formule à l'ouverture du fichier.
A11: Comment il a été produit
A12: Les colonnes descriptives sont lues dans le code du jeu : elles ne peuvent pas diverger de ce qui se joue.
A13: Le fichier est régénérable à chaque version. C'est une photographie du jeu, pas un document à éditer à la main :
A14: une correction saisie ici serait perdue à la prochaine génération, et elle ne changerait rien au jeu.
... A24: Seules les colonnes Ancrage réel daté et Limite documentée renvoient à des faits, et chacune porte sa date.

Sheet Catalogue
A1: ID | B1: Camp | C1: Famille | D1: Levier | E1: Alias polémique | F1: Portée | G1: Coût politique | H1: Coût capital | I1: Coût attention | J1: Latence (tours) | K1: Seuil de perçu | L1: Époque | M1: Prérequis | N1: Réussite (%) | O1: Réversibilité | P1: Robustesse | Q1: Contre-levier | R1: Piège | S1: Combinaisons | T1: Puissance réelle (1-5) | U1: Effet dans le jeu | V1: Mécanisme | W1: Ancrage réel daté | X1: Limite documentée | Y1: Rôle dans le jeu (arbitrage août)
A2: A01 | B2: Actif | C2: Réglementaire | D2: Tarification carbone nationale | E2: matraquage fiscal | F2: Bloc | G2: 4 | K2: 45 | L2: 1 | N2: 78 | O2: Facile à annuler | P2: Élevée | Q2: T60 | S2: Le chèque avec la taxe (avec A31) | T2: 4 | U2: Contrainte +20, friction +22. Friction divisée par deux si la redistribution a été installée. | V2: Un prix sur la tonne renchérit l'usage fossile dans toute l'économie du bloc, sans désigner de secteur. L'effet est large mais la douleur est visible et datée. | W2: Taxe carbone française 2014-2018, gelée en décembre 2018 après les Gilets jaunes. Prix du carbone suédois autour de 120 €/t depuis 2018, maintenu. | X2: Sans redistribution visible, la friction s'accumule jusqu'au retour de flamme : taxe française gelée en 2018, tarification australienne abrogée en 2014. | Y2: Noyau · Émissions — la tarification icônique, et le générateur de friction du jeu (paire avec A31)
A3: A02 | B3: Actif | C3: Réglementaire | D3: Marché de quotas (ETS) | E3: usine à gaz bruxelloise | F3: Bloc | G3: 3 | K3: 45 | L3: 1 | N3: 100 | O3: Difficile à annuler | P3: Élevée | Q3: T22 | S3: Plafond étanche (avec A03) | T3: 4 | U3: Contrainte +18, friction +9. | V3: Plafond décroissant sur les émetteurs, échangeable. Le coût passe par les prix sans jamais apparaître comme un impôt : friction citoyenne faible. | W3: EU ETS depuis 2005 ; prix passé de 5 € (2017) à plus de 80 €/t (2023). ETS2 bâtiment et transport prévu pour 2027. | X3: Vulnérable aux exemptions sectorielles obtenues discrètement : le plafond tient, le périmètre se vide. | Y3: Noyau · Émissions — l'outil de fond, plafond décroissant, faible friction citoyenne
A4: A03 | B4: Actif | C4: Réglementaire | D4: Ajustement carbone aux frontières | E4: protectionnisme vert | F4: Bloc | G4: 4 | K4: 35 | L4: 2 | M4: un prix du carbone intérieur — sans lui, il n'y a rien à ajuster à la frontière | N4: 100 | O4: Difficile à annuler | P4: Moyenne | Q4: T53 | S4: Plafond étanche (avec A02) | T4: 3 | U4: Contrainte +12 ici, +5 sur les autres blocs riches. Immunise le bloc contre le whataboutisme. | V4: Taxe l'empreinte des importations au niveau du prix intérieur. Supprime l'argument « nos usines partiront ailleurs » en supprimant l'avantage du moins-disant. | W4: MACF/CBAM européen : phase déclarative depuis octobre 2023, financière à partir de 2026. | X4: Provoque des représailles commerciales et des accusations de protectionnisme vert de la part des blocs exportateurs. | Y4: Noyau · Émissions — contre structurel du whataboutisme (T02) et de la fuite de carbone (T53)
A5: A04 | B5: Actif | C5: Réglementaire | D5: Norme d'émission véhicules | E5: norme punitive | F5: Bloc | G5: 2 | J5: 1 | L5: 1 | N5: 100 | O5: Difficile à annuler | P5: Élevée | Q5: T52 | T5: 4 | U5: Contrainte +19 au tour suivant, friction +7. | V5: Contraint les constructeurs, pas les conducteurs. Le coût est industriel, invisible du citoyen, et l'effet court sur tout le parc renouvelé. | W5: Règlement européen 95 gCO₂/km ; fin du thermique neuf actée pour 2035, avec clause de revoyure 2026. | X5: Cible privilégiée des exemptions technologiques : une niche inscrite dans le texte suffit à en vider l'effet. | Y5: Noyau · Émissions — contrainte industrielle sans coût budgétaire ; contre direct de T52
A6: A05 | B6: Actif | C6: Réglementaire | D6: Interdiction de vente datée | E6: interdiction idéologique | F6: Bloc | G6: 4 | J6: 1 | K6: 55 | L6: 2 | N6: 72 | O6: Facile à annuler | P6: Moyenne | Q6: T71 | T6: 5 | U6: Contrainte +27 au tour suivant, friction +17. | V6: Une date butoir déclenche l'anticipation industrielle bien avant l'échéance : les investissements se réorientent dès l'annonce. | W6: Fin du thermique neuf 2035 (UE) ; interdiction des chaudières fioul en France en 2022 ; interdiction des ampoules à incandescence. | X6: Plus la date est lointaine, plus elle est facile à voter et à annuler. Une clause de revoyure suffit à la rouvrir. | Y6: Noyau · Émissions — déclenche l'anticipation industrielle dès l'annonce (puissance 5)
A7: A07 | B7: Actif | C7: Réglementaire | D7: Fin des subventions aux fossiles | E7: hausse des prix à la pompe | F7: Mondial | G7: 5 | L7: 1 | N7: 50 | O7: Facile à annuler | P7: Élevée | Q7: T39 | T7: 5 | U7: Contrainte +9 et friction +11 sur tous les blocs. | V7: Supprime la subvention à la consommation fossile. Aucune technologie à déployer, aucun délai de mise en œuvre : seulement une décision budgétaire. | W7: Engagement du G20 depuis 2009 ; subventions explicites toujours de l'ordre de 1 200 Md$/an selon le FMI. | X7: Politiquement très difficile : dans plusieurs blocs, le prix subventionné du carburant tient lieu de contrat social, et sa suppression a déclenché des émeutes. | Y7: Noyau · Émissions — meilleur rapport effet/coût du catalogue, portée mondiale
A8: A09 | B8: Actif | C8: Narratif | D8: Objectif net zéro 2050 | F8: Mondial | I8: 1 | L8: 1 | N8: 100 | O8: Facile à annuler | P8: Faible | Q8: A12 | R8: oui | T8: 1 | U8: Perçu +9 partout immédiatement. Aucune contrainte, jamais. | V8: Marque des points d'opinion sans engager la moindre décision : aucune étape intermédiaire, aucun décideur en exercice concerné. | W8: Généralisation des annonces net zéro 2050 sans trajectoire 2030 intermédiaire. | X8: Un objectif à trente-cinq ans sans étape intermédiaire n'engage aucun décideur en exercice. Les émissions, elles, se comptent chaque année. | Y8: Noyau · Piège — le plus répandu. Points d'opinion immédiats, zéro tonne évitée
A9: A10 | B9: Actif | C9: Réglementaire | D9: Normes d'efficacité des appareils | F9: Bloc | G9: 1 | L9: 1 | N9: 100 | O9: Difficile à annuler | P9: Élevée | Q9: T73 | T9: 3 | U9: Contrainte +11, friction +1. Aucun contre-levier connu. | V9: Retire du marché les produits les moins efficaces. Effet cumulatif sur des décennies, sans que personne ne s'en aperçoive. | W9: Étiquetage énergétique et écoconception UE ; sortie de l'incandescence. Consommation moyenne d'un réfrigérateur divisée par trois depuis 1990. | X9: Aucun effet spectaculaire, donc aucun gain d'opinion — et aussi peu de prise pour l'adversaire, qui n'a pas d'angle d'attaque sur un seuil technique. | Y9: Noyau · Émissions — le levier invisible : coût 1, aucun contre-levier. Enseigne que l'efficace n'est pas spectaculaire
A10: A11 | B10: Actif | C10: Réglementaire | D10: Réduction des fuites de méthane | E10: contrainte sur les éleveurs | F10: Bloc | G10: 2 | K10: 25 | L10: 1 | N10: 100 | O10: Difficile à annuler | P10: Élevée | Q10: T22 | S10: Le coup de Kigali (avec A67) | T10: 4 | U10: Contrainte +13, friction +2. Effet en quelques années, contre une à deux décennies pour la plupart des autres. | V10: Le méthane a un pouvoir de réchauffement 80 fois supérieur au CO₂ sur vingt ans, mais une durée de vie courte : colmater agit dans la décennie, pas dans le siècle. | W10: Global Methane Pledge (2021), plus de 150 signataires ; règlement méthane européen (2024) ; détection satellitaire opérationnelle depuis 2023. | X10: Ne remplace rien : c'est un gain de temps, pas une trajectoire. Le CO₂ reste le stock qui compte. | Y10: Noyau · Émissions — le SEUL levier actif à effet rapide. Indispensable à l'équilibrage
A11: A12 | B11: Actif | C11: Réglementaire | D11: Loi-cadre climat contraignante | E11: carcan juridique | F11: Bloc | G11: 5 | K11: 55 | L11: 2 | N11: 62 | O11: Irréversible | P11: Élevée | Q11: T21 | S11: Trajectoire opposable (avec A63) | T11: 5 | U11: Verrouille le bloc : les mesures y résistent au retour de flamme et aux exemptions. | V11: Inscrit une trajectoire et un budget carbone dans la loi. Les mesures suivantes deviennent l'exécution d'une obligation, plus des choix révocables. | W11: UK Climate Change Act (2008), adopté à cinq voix contre. Loi Énergie-Climat française (2019). | X11: Exige un perçu élevé au moment du vote. Après polarisation, la fenêtre se referme pour toute la partie. | Y11: Pilier · Verrou — budgets pluriannuels contraignants, chaque écart devient attaquable
A12: A15 | B12: Actif | C12: Réglementaire | D12: Reporting extra-financier obligatoire | E12: paperasse extra-financière | F12: Bloc | G12: 2 | L12: 2 | N12: 100 | O12: Facile à annuler | P12: Moyenne | Q12: T70 | T12: 3 | U12: Contrainte +7 et perçu +5 : l'exposition carbone devient visible des investisseurs. | V12: Ce qui est mesuré et publié devient un risque financier. Le capital se retire avant que la réglementation ne morde. | W12: CSRD européenne (2022), largement allégée par le paquet omnibus de 2025. | X12: Démontré détricotable : la simplification administrative vide la norme sans jamais l'abroger. | Y12: Noyau · Verrou — PROMU : contre-levier de quatre cartes du noyau (T05, T20, T51, P01). Charnière de la couche institutionnelle
A13: A17 | B13: Actif | C13: Réglementaire | D13: Interdiction de la publicité fossile | E13: censure publicitaire | F13: Bloc | G13: 2 | K13: 40 | L13: 2 | N13: 70 | O13: Facile à annuler | P13: Moyenne | Q13: T31 | S13: Coupure médiatique (avec A54) | T13: 2 | U13: L'adversaire perd 1 point d'Attention pendant deux tours. | V13: Coupe l'accès du camp adverse à sa ressource principale. Effet indirect, mais il s'applique à toutes ses campagnes suivantes. | W13: Amsterdam (2020) ; loi Climat et Résilience française (2021), périmètre finalement restreint au fossile pur. | X13: Le greenwashing contourne l'interdiction en déplaçant le message vers l'entreprise plutôt que le produit. | Y13: Signature — le seul levier actif qui attaque directement la ressource Attention adverse
A14: A18 | B14: Actif | C14: Économique | D14: Subvention massive au déploiement | E14: gouffre à subventions | F14: Mondial | H14: 5 | J14: 2 | L14: 1 | N14: 100 | O14: Difficile à annuler | P14: Élevée | Q14: T67 | S14: La courbe s'effondre (avec A40) | T14: 5 | U14: Indice technologique +18 dans deux tours. Profite à tous les blocs, y compris à l'adversaire. | V14: Payer le déploiement fait descendre la courbe d'apprentissage. Le prix baisse pour tout le monde, définitivement. | W14: EEG allemand 2000-2015, environ 200 Md€, à l'origine de la chute mondiale du prix du photovoltaïque (−90 % entre 2010 et 2020). | X14: Passager clandestin inversé : vous payez, les autres blocs en bénéficient gratuitement. Le gain d'opinion national est nul. | Y14: Noyau · Émissions — courbe d'apprentissage : payé par un bloc, bénéficie à tous. Prouve mécaniquement que l'action marche
A15: A19 | B15: Actif | C15: Économique | D15: Politique industrielle verte | E15: subventions clientélistes | F15: Bloc | H15: 5 | L15: 1 | N15: 100 | O15: Facile à annuler | P15: Élevée | Q15: T50 | T15: 4 | U15: Contrainte +16, friction −4. Achète l'adhésion au lieu de contraindre. | V15: Crédits d'impôt et commandes publiques rendent la décarbonation rentable. Les industriels deviennent la coalition au lieu de l'opposition. | W15: Inflation Reduction Act américain (2022), environ 369 Md$ climat ; Net-Zero Industry Act européen. | X15: Cible directe de la capture de subvention : l'aide est encaissée sans que la trajectoire change. | Y15: Noyau · Coalition — acheter l'adhésion plutôt que contraindre ; cible du piège T50
A16: A20 | B16: Actif | C16: Économique | D16: Contrat pour différence | E16: prix garantis à vie | F16: Bloc | H16: 3 | L16: 2 | M16: une politique industrielle ou une subvention au déploiement déjà engagée | N16: 100 | O16: Difficile à annuler | P16: Élevée | Q16: T66 | S16: Capital dérisqué (avec A21) | T16: 4 | U16: Contrainte +14, et plafond +6 s'il a été abaissé par l'adversaire. Le coût du capital chute. | V16: L'État garantit un prix de vente. Le risque disparaît, le taux d'actualisation s'effondre, le projet se finance. | W16: CfD britanniques sur l'éolien en mer : prix adjugés divisés par trois entre 2015 et 2022. | X16: Levier discret et sans récit : il ne rapporte aucun point d'opinion, ce qui le rend rarement prioritaire. | Y16: Noyau · Émissions — PROMU : contre du piège P07. C'est le CfD qui rend le CCS sur centrale économiquement absurde
A17: A21 | B17: Actif | C17: Technologique | D17: Réseau électrique et stockage | F17: Bloc | H17: 4 | L17: 1 | N17: 100 | O17: Difficile à annuler | P17: Élevée | Q17: T40 | S17: Capital dérisqué (avec A20) | T17: 4 | U17: Contrainte +6, et plafond +18 s'il a été abaissé. Prérequis physique de tous les leviers électriques. | V17: Sans réseau ni flexibilité, l'électrification sature : les renouvelables sont écrêtés et les usages ne basculent pas. | W17: Files d'attente de raccordement de plusieurs années en Europe et aux États-Unis ; le réseau est devenu le premier goulot. | X17: Aucun effet visible dans le tour. C'est un levier qui n'existe que par ce qu'il rend possible ensuite. | Y17: Noyau · Émissions — prérequis physique : sans réseau, les leviers électriques saturent
A18: A22 | B18: Actif | C18: Économique | D18: Compensation carbone volontaire | F18: Bloc | H18: 1 | L18: 1 | N18: 100 | O18: Facile à annuler | P18: Faible | Q18: A15 | R18: oui | T18: 1 | U18: Contrainte +2 seulement. Crédibilité −8 quand l'écart est révélé. | V18: Semble neutraliser vos émissions résiduelles pour presque rien. Le crédit est réel, la réduction ne l'est pas. | W18: Revue de 25 ans de projets forestiers : majorité jugée non additionnelle. Marché volontaire en baisse de plus de 60 % depuis 2022. | X18: Le prix est le signal : une tonne réellement évitée ne coûte pas trois euros. Le crédit est réel, la réduction sous-jacente rarement additionnelle. | Y18: Noyau · Piège — le piège n°1, documenté, marché effondré de plus de 60 %
A19: A25 | B19: Actif | C19: Économique | D19: Désinvestissement institutionnel | E19: vendre pour l'exemple | F19: Mondial | H19: 2 | L19: 1 | N19: 100 | O19: Facile à annuler | P19: Contestée | Q19: T46 | R19: oui | T19: 2 | U19: Perçu +9 partout. Contrainte +1 seulement : le signal est réel, l'effet sur le coût du capital ne l'est pas. | V19: Vendre un titre ne retire pas un euro à l'entreprise : il change de porteur au prix du marché. L'effet passe par la stigmatisation et par le signal donné aux autres investisseurs. | W19: Mouvement de désinvestissement depuis 2012 ; exclusions du fonds souverain norvégien. Les travaux empiriques ne mettent pas en évidence d'effet mesurable sur le coût du capital des majors. | X19: Le titre vendu est racheté, souvent par un acteur moins exposé à la pression publique. Le levier déplace la propriété, pas les émissions — et il consomme le capital qui aurait financé une contrainte réelle. | Y19: Extension · robustesse contestée — candidat sérieux au statut de PIÈGE plutôt que de levier
A20: A26 | B20: Actif | C20: Technologique | D20: Programme nucléaire accéléré | F20: Bloc | H20: 5 | L20: 3 | N20: 100 | O20: Difficile à annuler | P20: Faible | Q20: A46 | R20: oui | T20: 1 | U20: Contrainte +3 et plafond −6 : le budget part, la centrale arrive après la partie. | V20: Le levier est réel sur l'horizon long. Présenté comme réponse à la décennie, il sert d'argument de report. | W20: Délais de douze à dix-sept ans par réacteur ; Flamanville, douze ans de retard. | X20: Le programme est légitime sur l'horizon long — voir A46. Présenté comme réponse à la décennie, il mobilise un budget aujourd'hui pour une production qui arrive après la partie. | Y20: Noyau · Piège — le levier nucléaire est réel (A46), c'est le CALENDRIER qui est le piège. Évite que le jeu soit lu comme antinucléaire
A21: A27 | B21: Actif | C21: Économique | D21: Retrait de l'assurance sur les projets fossiles | E21: boycott financier | F21: Mondial | H21: 2 | L21: 2 | N21: 100 | O21: Facile à annuler | P21: Moyenne | Q21: T74 | T21: 4 | U21: Contrainte +7 sur les cinq blocs à rente fossile élevée (AN, AS, GR, AL, AF). Un projet non assurable ne se finance pas. | V21: Sans couverture, aucune banque ne prête. Le verrou est privé, donc hors de portée du législateur adverse. | W21: Retraits successifs des réassureurs sur le charbon et les sables bitumineux depuis 2017. | X21: Des assureurs de second rang et des captives publiques prennent le relais dans les blocs à rente élevée. | Y21: Noyau · Verrou — un projet non assurable ne se finance pas ; branche sur la mécanique de retrait assurantiel
A22: A28 | B22: Actif | C22: Économique | D22: Suppression des niches fiscales sectorielles | E22: la fin des privilèges | F22: Bloc | G22: 3 | K22: 40 | L22: 2 | N22: 100 | O22: Facile à annuler | P22: Élevée | Q22: T41 | T22: 3 | U22: Contrainte +13 et friction +18. Friction portée à +26 si le bloc a déjà subi une campagne territoriale. | V22: Kérosène, gazole non routier, exonérations sectorielles : le gain budgétaire est immédiat et la cible est étroite, donc parfaitement organisée pour se défendre. | W22: Suppression progressive de l'exonération sur le gazole non routier agricole annoncée en France fin 2023, retirée en février 2024 après la mobilisation. | X22: Une niche défendue par une profession identifiable produit une fracture professionnelle, pas une contestation diffuse : elle est plus violente et plus courte. | Y22: Extension · déclenche la fracture professionnelle (paire avec T41) — à réintégrer tôt
A23: A29 | B23: Actif | C23: International | D23: Financement climat Nord-Sud | E23: chèque en blanc | F23: Mondial | H23: 5 | L23: 1 | N23: 100 | O23: Facile à annuler | P23: Moyenne | Q23: T02 | S23: Confiance multilatérale (avec A65) | T23: 4 | U23: Contrainte +10 et perçu +6 sur l'Inde, l'Afrique, l'Amérique latine et le reste de l'Asie. | V23: Le capital est le facteur limitant des blocs émergents, pas la volonté. Le financement lève directement la contrainte. | W23: 100 Md$/an promis en 2009, atteints en 2022 ; nouvel objectif de 300 Md$/an acté à Bakou en 2024. | X23: Sans lui, aucun accord mondial ne tient. Avec lui, la facture est visible chez vous et invisible ailleurs. | Y23: Noyau · Coalition — sans lui aucun accord mondial ne tient ; contre de T02
A24: A31 | B24: Actif | C24: Économique | D24: Redistribution du produit de la taxe | E24: redistribution électoraliste | F24: Bloc | H24: 3 | L24: 1 | M24: une tarification carbone en vigueur — sans produit, il n'y a rien à redistribuer | N24: 100 | O24: Facile à annuler | P24: Élevée | Q24: T08 | S24: Le chèque avec la taxe (avec A01) | T24: 4 | U24: Friction −26 et compensation durable installée sur le bloc. | V24: Rendre le produit sous forme de chèque visible transforme un impôt en transfert. La mesure survit à l'alternance. | W24: Dividende carbone canadien, chèque trimestriel identifiable. Absence de redistribution lisible en France en 2018. | X24: Carte ennuyeuse et décisive : sans elle, la tarification ne passe pas deux tours. | Y24: Noyau · Coalition — carte ennuyeuse et décisive. Sans elle, A01 ne survit pas à T39
A25: A33 | B25: Actif | C25: Judiciaire | D25: Contentieux climatique contre l'État | E25: gouvernement des juges | F25: Bloc | H25: 2 | L25: 1 | N25: 72 | O25: Difficile à annuler | P25: Élevée | Q25: T26 | T25: 4 | U25: Contrainte +12 sans condition de soutien perçu. Sans effet en régime autoritaire. | V25: Contourne l'arène électorale : le juge impose ce que la majorité ne vote pas. Le seul levier qui ignore la jauge d'opinion. | W25: Urgenda (Pays-Bas, 2019), Affaire du Siècle (France, 2021), Neubauer (Allemagne, 2021). | X25: Gagner un procès n'exécute rien : l'État condamné peut payer et continuer. | Y25: Noyau · Verrou — contourne l'arène électorale par le juge
A26: A35 | B26: Actif | C26: Judiciaire | D26: Recours devant une cour régionale des droits humains | E26: juges étrangers | F26: Mondial | H26: 3 | J26: 1 | L26: 2 | M26: un contentieux national déjà porté — on ne saisit pas la cour régionale d'emblée | N26: 58 | O26: Irréversible | P26: Élevée | Q26: T24 | T26: 4 | U26: Contrainte +9 au tour suivant sur tous les blocs démocratiques. | V26: Crée une obligation opposable à tous les États membres d'un seul coup, sans passer par aucun parlement. | W26: CEDH, KlimaSeniorinnen contre Suisse, avril 2024 : première condamnation d'un État pour inaction climatique par une cour des droits humains. | X26: Ne touche que les blocs soumis à la juridiction. Les plus gros émetteurs n'y sont pas. | Y26: Pilier · Verrou — irréversible, multi-bloc d'un seul coup (KlimaSeniorinnen 2024)
A27: A36 | B27: Actif | C27: Judiciaire | D27: Avis consultatif de juridiction internationale | E27: droit mou international | F27: Mondial | G27: 3 | J27: 2 | L27: 3 | M27: un contentieux climatique déjà engagé | N27: 52 | O27: Irréversible | P27: Élevée | Q27: T24 | S27: La sortie par le droit (avec A71) | T27: 4 | U27: Contrainte +6 partout dans deux tours. Neutralise l'arbitrage investisseur-État pendant deux tours. | V27: Établit que les obligations climatiques relèvent du droit international général : toutes les procédures suivantes s'y adossent. | W27: Avis consultatif de la Cour internationale de justice sur les obligations des États, 23 juillet 2025. | X27: Non contraignant en lui-même. Sa force est entièrement dans ce que les juges nationaux en font ensuite. | Y27: Pilier · Verrou — irréversible mondial, ouvre la voie aux réparations (CIJ 2025)
A28: A37 | B28: Actif | C28: Judiciaire | D28: Contentieux publicité mensongère | E28: police de la parole | F28: Bloc | G28: 2 | H28: 1 | L28: 2 | N28: 66 | O28: Difficile à annuler | P28: Élevée | Q28: T26 | S28: Le dossier et le procès (avec A54) | T28: 2 | U28: Retire l'emprise médiatique installée sur le bloc et rend 10 de soutien perçu. Sans emprise à défaire, l'action ne rend que 4. Crédibilité adverse −6. | V28: Une campagne qui présente une activité fossile comme neutre en carbone est une allégation commerciale, pas une opinion. Elle se juge sur la preuve, et la preuve manque. | W28: Décisions de l'ASA britannique contre des campagnes pétrolières ; plainte française contre TotalEnergies pour pratiques commerciales trompeuses, 2022. | X28: Le retrait de la campagne arrive après qu'elle a produit son effet. Le procès défait l'emprise, il ne rend pas les tours perdus. | Y28: Extension · redondant avec A17 dans le noyau
A29: A38 | B29: Actif | C29: Technologique | D29: Captage et stockage sur centrale électrique | F29: Bloc | H29: 5 | J29: 2 | L29: 2 | N29: 100 | O29: Difficile à annuler | P29: Faible | Q29: A20 | R29: oui | T29: 1 | U29: Contrainte +4 dans deux tours, pour un coût de 5. Prolonge le parc fossile. | V29: Techniquement possible, économiquement absurde face au renouvelable : on paie deux fois pour produire la même électricité. | W29: Boundary Dam et Petra Nova : taux de captage réels très inférieurs aux annonces, arrêts prolongés. | X29: La même technologie est défendable sur le ciment et la chimie, où la réaction elle-même émet — voir A44. Sur une centrale, elle revient à payer deux fois pour la même électricité. | Y29: Noyau · Piège — pendant piège de A44 : même technologie, un usage légitime, un usage piège
A30: A39 | B30: Actif | C30: Technologique | D30: R&D publique | F30: Bloc | H30: 3 | J30: 3 | L30: 1 | N30: 100 | O30: Difficile à annuler | P30: Moyenne | Q30: T68 | T30: 2 | U30: Indice technologique +14 dans trois tours. Aucun effet immédiat. | V30: Prépare les leviers des tours suivants. Le seul levier dont le rendement est entièrement reporté. | W30: Mission Innovation lancée en 2015 en marge de la COP21 ; budgets publics de R&D énergie. | X30: Ne remplace jamais le déploiement : chercher sans déployer ne fait pas baisser les prix. | Y30: Noyau · Émissions — PROMU : contre de T04 (optimisme technologique), et seule carte qui enseigne la latence pure
A31: A40 | B31: Actif | C31: Technologique | D31: Électrification des usages | E31: tout-électrique forcé | F31: Bloc | H31: 3 | K31: 40 | L31: 2 | M31: le réseau électrique et le stockage — prérequis physique de l'électrification | N31: 100 | O31: Difficile à annuler | P31: Élevée | Q31: A42 | S31: La courbe s'effondre (avec A18) | T31: 5 | U31: Contrainte +16, augmentée par l'indice technologique. Friction +5. | V31: Un moteur électrique convertit trois à quatre fois mieux qu'un moteur thermique. Le gain est physique, avant même de décarboner le mix. | W31: Ventes de voitures électriques passées de 1 % à plus de 20 % du marché mondial entre 2015 et 2024. | X31: Sature si le réseau n'a pas été renforcé. Ciblée par les faux vecteurs alternatifs. | Y31: Noyau · Émissions — multiplicateur de toute décarbonation du mix (puissance 5)
A32: A41 | B32: Actif | C32: Économique | D32: Plan de sobriété organisée | E32: rationnement déguisé | F32: Bloc | G32: 2 | L32: 2 | N32: 100 | O32: Facile à annuler | P32: Moyenne | Q32: T09 | T32: 3 | U32: Contrainte +9 dès ce tour, friction +5, perçu +3. Le seul levier actif dont l'effet tombe entièrement dans le tour. | V32: Consignes de température, décalage des usages, pilotage de la pointe. Ce n'est pas de la contrainte individuelle mais du pilotage administratif d'une consommation collective. | W32: Plan de sobriété français de l'hiver 2022 : environ 12 % de consommation de gaz en moins à conditions climatiques corrigées, sans coupure. | X32: L'effet ne survit pas à la campagne qui le porte. Sans mesure structurelle derrière, la consommation revient à son niveau en deux ans. | Y32: Extension · effet immédiat rare côté actif — à réintégrer si l'équilibrage montre l'actif trop lent
A33: A42 | B33: Actif | C33: Technologique | D33: Hydrogène pour la voiture particulière | F33: Bloc | H33: 4 | J33: 2 | L33: 2 | N33: 100 | O33: Difficile à annuler | P33: Faible | Q33: A40 | R33: oui | T33: 1 | U33: Contrainte +3 dans deux tours, pour un coût de 4. Retarde l'électrification directe. | V33: Rendement global trois à quatre fois inférieur à la batterie : électrolyse, compression, pile à combustible, chaque étape perd. | W33: Abandons successifs des programmes hydrogène automobile depuis 2020 ; parc mondial resté marginal. | X33: Le même vecteur est pertinent là où l'électrification directe est impossible — industrie, maritime, voir A47. Sur la voiture particulière, il coûte trois à quatre fois plus d'électricité pour le même kilomètre. | Y33: Noyau · Piège — rendement 3 à 4 fois inférieur à l'électrique à batterie. Pendant piège de A47
A34: A43 | B34: Actif | C34: Technologique | D34: Carburants de synthèse pour l'automobile | F34: Bloc | H34: 4 | L34: 3 | N34: 100 | O34: Difficile à annuler | P34: Faible | Q34: A04 | R34: oui | T34: 1 | U34: Contrainte +2 et plafond −8 : ouvre une exemption réglementaire durable. | V34: Coût et rendement prohibitifs à l'échelle. Sert surtout à maintenir légalement le moteur thermique. | W34: Exemption e-fuels obtenue en 2023 sur le règlement européen de fin du thermique en 2035. | X34: Le coût et le rendement restent prohibitifs à l'échelle du parc automobile. Dans les faits, la filière a surtout servi à obtenir une exemption au règlement de 2035. | Y34: Noyau · Piège — devient une exemption réglementaire réelle (paire avec T52)
A35: A44 | B35: Actif | C35: Technologique | D35: Captage sur émissions industrielles | F35: Bloc | H35: 5 | K35: 30 | L35: 3 | N35: 100 | O35: Difficile à annuler | P35: Contestée | Q35: T69 | T35: 2 | U35: Contrainte +8 seulement, sans friction. Utile là où rien d'autre n'existe. | V35: Ciment et chimie émettent par la réaction elle-même, pas par la combustion : l'électrification n'y peut rien. | W35: Sous-performance documentée de Boundary Dam et Petra Nova, taux de captage réels inférieurs aux annonces. | X35: La même technologie appliquée à la production électrique produit l'effet inverse : elle prolonge le parc fossile au lieu de traiter des émissions qu'aucune autre technique ne réduit. | Y35: Extension · paire pédagogique avec le piège P07 — réintégrer avec P07 ou pas du tout
A36: A46 | B36: Actif | C36: Technologique | D36: Programme nucléaire | F36: Bloc | H36: 5 | J36: 3 | L36: 2 | N36: 100 | O36: Difficile à annuler | P36: Élevée | Q36: T72 | T36: 3 | U36: Contrainte +15 dans trois tours, friction +8 immédiate. | V36: Effet réel et durable sur le mix, avec un délai de douze à dix-sept ans par réacteur. Le calendrier est le sujet, pas la technologie. | W36: Relance EPR2 en France (2022) ; dérives de Flamanville et Hinkley Point C. | X36: Fracture la coalition écologiste. Et le même programme, présenté comme une réponse à l'échéance de 2030 plutôt qu'à celle de 2050, sert d'argument à repousser tout le reste : la technologie est honnête, le calendrier qu'on lui prête ne l'est pas toujours. | Y36: Signature — fracture la coalition écologiste. Arme à double tranchant, incontournable en contexte français. Paire avec le piège P10
A37: A47 | B37: Actif | C37: Technologique | D37: Hydrogène pour l'industrie et le maritime | F37: Bloc | H37: 5 | J37: 2 | L37: 3 | M37: le réseau électrique, ou un indice technologique d'au moins 25 | N37: 100 | O37: Difficile à annuler | P37: Contestée | Q37: T69 | T37: 2 | U37: Contrainte +9 dans deux tours. | V37: Pertinent là où l'électrification directe est impossible : acier, ammoniac, navires longue distance. | W37: Stratégies hydrogène européennes et nationales depuis 2020, révisées à la baisse en 2024-2025. | X37: Le même vecteur appliqué à la voiture particulière perd les trois quarts de l'énergie en conversions successives, là où la batterie fait le trajet directement. | Y37: Extension · paire pédagogique avec le piège P04 — réintégrer avec P04 ou pas du tout
A38: A48 | B38: Actif | C38: Réglementaire | D38: Réduction des émissions agricoles | E38: agribashing | F38: Bloc | G38: 5 | K38: 50 | L38: 2 | N38: 56 | O38: Facile à annuler | P38: Moyenne | Q38: T41 | T38: 4 | U38: Contrainte +13, friction +20. Le secteur le plus verrouillé politiquement. | V38: Méthane entérique, fertilisation azotée, cheptel. Un cinquième des émissions mondiales, presque jamais contraint. | W38: Objectifs agricoles retirés du Pacte vert européen après les mobilisations de 2024. | X38: Déclenche mécaniquement la fracturation de la coalition : c'est le levier préféré de l'adversaire pour détacher un groupe social. | Y38: Noyau · Émissions — le secteur le plus verrouillé politiquement ; paire avec T41
A39: A49 | B39: Actif | C39: Narratif | D39: Attribution rapide d'un événement extrême | E39: science militante | F39: Mondial | I39: 2 | L39: 1 | N39: 100 | O39: Facile à annuler | P39: Élevée | Q39: T36 | S39: Fenêtre d'attention (avec A50) | T39: 3 | U39: Perçu +10 sur le bloc frappé, +4 ailleurs. Immunise contre la saturation ce tour-ci. | V39: Sans étude d'attribution, une catastrophe reste un fait divers météorologique. Avec, elle devient une conséquence datée et chiffrée. | W39: World Weather Attribution publie des études en quelques jours depuis 2015 ; canicule européenne de 2022 rendue au moins dix fois plus probable. | X39: La fenêtre se referme en une semaine. Jouée trop tard, la carte ne déplace plus rien. | Y39: Pilier · Opinion — mécanique centrale d'attribution. Sans elle, aucune catastrophe ne déplace de jauge
A40: A50 | B40: Actif | C40: Narratif | D40: Révéler la majorité silencieuse | E40: sondage militant | F40: Bloc | I40: 2 | L40: 1 | N40: 100 | O40: Facile à annuler | P40: Élevée | Q40: T33 | S40: Fenêtre d'attention (avec A49) | T40: 4 | U40: Le perçu rattrape 60 % de son écart avec le soutien réel. Deux usages par partie. | V40: Les gens sous-estiment massivement le soutien des autres et se taisent en conséquence. Publier le chiffre réel casse la spirale du silence. | W40: Andre et al., Nature Climate Change 2024 : 69 % de soutien réel pour 43 % de soutien perçu, dans 125 pays. | X40: Ne crée rien : ne fait que révéler ce qui existe déjà. Sur un bloc au soutien réel faible, elle ne sert à rien. | Y40: Pilier · Opinion — mécanique signature du jeu (écart 69 % réel / 43 % perçu). Usage limité par partie
A41: A51 | B41: Actif | C41: Narratif | D41: Mobilisation de masse | E41: militantisme de rue | F41: Mondial | I41: 3 | L41: 1 | N41: 100 | O41: Facile à annuler | P41: Moyenne | Q41: T36 | T41: 3 | U41: Perçu +14 sur les trois blocs les plus favorables, puis −6 au tour suivant. | V41: Rouvre la fenêtre politique en rendant le soutien visible dans la rue. Effet fort et rapidement amorti. | W41: Marches climat mondiales de septembre 2019, plusieurs millions de participants ; reflux net après 2020. | X41: Un mouvement ne se rallume pas deux fois au même endroit. La démobilisation est plus rapide que la mobilisation. | Y41: Noyau · Opinion — effet fort et rapidement amorti : bonne courbe de décision
A42: A52 | B42: Actif | C42: Narratif | D42: Désobéissance civile | E42: blocage illégal | F42: Bloc | G42: 1 | I42: 1 | L42: 2 | N42: 58 | O42: Facile à annuler | P42: Contestée | Q42: T27 | S42: Le flanc et le centre (avec A57) | T42: 2 | U42: Soutien réel +9, perçu −6, friction +8, et votre crédibilité perd 8. Le seul levier qui peut vous coûter plus qu'il ne rapporte. | V42: Le flanc radical déplace la fenêtre : ce qui paraissait extrême devient le compromis, et l'organisation modérée qui négocie à côté paraît raisonnable. Le soutien de fond monte pendant que l'opinion affichée se braque. | W42: Just Stop Oil au Royaume-Uni et Dernière Rénovation en France depuis 2022 ; littérature empirique sur l'effet de flanc radical, dont les résultats restent partagés. | X42: L'effet net est contesté et il est retardé : le perçu tombe tout de suite, le réel ne se convertit qu'au fil des tours. Joué trop tard, il ne rapporte rien et coûte la crédibilité. | Y42: Extension · effet net contesté, peut nuire au camp qui le joue. Excellente carte à risque, à tester en priorité
A43: A53 | B43: Actif | C43: Narratif | D43: Éducation et formation | E43: endoctrinement scolaire | F43: Bloc | H43: 2 | J43: 1 | L43: 1 | N43: 100 | O43: Irréversible | P43: Élevée | Q43: T61 | T43: 3 | U43: Soutien réel +5 sur le bloc, définitivement. Aucun contre-levier. | V43: Déplace le soutien réel et non le perçu — le seul de ce catalogue à le faire. Ce qui est acquis ici ne se reperd pas. | W43: Intégration des enjeux climatiques dans les cursus ; formation des cadres dirigeants et des élus depuis 2019. | X43: Effet minuscule à l'échelle d'un tour. C'est un levier de fin de partie joué en début de partie. | Y43: Noyau · Opinion — le seul levier lent et sûr : déplace le réel, incontrable
A44: A54 | B44: Actif | C44: Narratif | D44: Journalisme d'investigation | E44: procès d'intention | F44: Bloc | H44: 3 | L44: 2 | N44: 100 | O44: Irréversible | P44: Élevée | Q44: T10 | S44: Coupure médiatique (avec A17) · Le dossier et le procès (avec A37) | T44: 3 | U44: Crédibilité adverse −14, perçu +6 sur le bloc. Un seul coup par cible. | V44: Révéler ce que l'adversaire savait et quand il le savait déplace le débat du désaccord vers le mensonge. | W44: Exxon Knew (2015) : projections internes exactes dès les années 1970, publiquement contredites ensuite. | X44: Cible directe des procédures-bâillon : la source peut être supprimée avant la publication suivante. | Y44: Noyau · Opinion — irréversible, détruit la crédibilité adverse. Un coup par cible
A45: A57 | B45: Actif | C45: Narratif | D45: Récit désirable plutôt que punitif | E45: communication d'État | F45: Bloc | I45: 2 | L45: 1 | N45: 100 | O45: Facile à annuler | P45: Moyenne | Q45: T09 | S45: Le flanc et le centre (avec A52) | T45: 4 | U45: Soutien réel +4 et friction −9. | V45: Décrire ce que l'on gagne plutôt que ce que l'on perd désarme la défense du mode de vie sans rien concéder sur le fond. | W45: Bascule des campagnes de rénovation vers le confort et la facture plutôt que la contrainte carbone. | X45: Inopérant si les mesures effectivement jouées sont punitives : le récit ne survit pas au démenti. | Y45: Noyau · Opinion — santé, facture, air : plus efficace que le récit catastrophe
A46: A59 | B46: Actif | C46: Électoral | D46: Faire du climat un enjeu de campagne | E46: instrumentalisation électorale | F46: Bloc | G46: 3 | K46: 50 | L46: 1 | N46: 64 | O46: Facile à annuler | P46: Élevée | Q46: T62 | T46: 3 | U46: Contrainte +14 si le perçu dépasse 50. Sinon la campagne est perdue : perçu −8. | V46: Convertit le soutien perçu en mandat. C'est le seul levier qui transforme une opinion en autorisation d'agir. | W46: Élections européennes de 2019, vague verte ; reflux net de 2024. | X46: Vérifier la jauge avant de jouer : sur un perçu bas, la carte se retourne intégralement. | Y46: Noyau · Coalition — convertit le soutien perçu en mandat ; échoue si la jauge perçue est basse
A47: A60 | B47: Actif | C47: Électoral | D47: Coalition climat, emploi et pouvoir d'achat | E47: clientélisme vert | F47: Bloc | G47: 4 | L47: 1 | N47: 100 | O47: Difficile à annuler | P47: Élevée | Q47: T41 | T47: 4 | U47: Friction −14 et immunité partielle contre l'instrumentalisation du coût de la vie. | V47: Vendre la politique climatique comme politique industrielle et sociale retire à l'adversaire son angle d'attaque principal. | W47: Architecture de l'Inflation Reduction Act, présenté comme une loi sur l'inflation et l'emploi. | X47: Coûte cher en concessions : chaque groupe rallié obtient son exemption. | Y47: Noyau · Coalition — immunise partiellement contre T39. Coûte cher en concessions
A48: A61 | B48: Actif | C48: Électoral | D48: Ancrage local et réseaux de villes | E48: écologie punitive municipale | F48: Bloc | G48: 2 | L48: 1 | N48: 84 | O48: Facile à annuler | P48: Élevée | Q48: T19 | T48: 3 | U48: Contrainte +8. Jouable même sur un bloc préempté. | V48: Contourne le blocage national par l'échelon urbain, où les majorités climatiques sont plus solides. | W48: C40 Cities ; Convention des maires. Zones à faibles émissions déployées dans plus de 300 villes européennes. | X48: Neutralisé par la préemption législative : plus de vingt États américains interdisent à leurs villes de bannir le gaz depuis 2020. | Y48: Noyau · Coalition — contourne le blocage national ; paire avec T19 (préemption)
A49: A62 | B49: Actif | C49: Électoral | D49: Dépolitisation et accord transpartisan | E49: confiscation du débat | F49: Bloc | G49: 5 | K49: 60 | L49: 3 | N49: 45 | O49: Irréversible | P49: Élevée | Q49: T38 | T49: 5 | U49: Verrouille le bloc et le rend insensible à la guerre culturelle pour le reste de la partie. | V49: Sortir le sujet du clivage partisan rend la politique insensible à l'alternance. C'est ce qui a permis au Climate Change Act de survivre à quatre alternances. | W49: Climate Change Act britannique de 2008, adopté à cinq voix contre, jamais abrogé depuis malgré quatre alternances. | X49: Presque impossible à obtenir après polarisation. Si la guerre culturelle a déjà été jouée ici, la carte est morte. | Y49: Pilier · Verrou — puissance 5, irréversible, presque impossible après polarisation. Objectif de fin de partie
A50: A63 | B50: Actif | C50: Électoral | D50: Institution indépendante de suivi | E50: comité Théodule | F50: Bloc | G50: 2 | L50: 1 | N50: 80 | O50: Difficile à annuler | P50: Élevée | Q50: T21 | S50: Trajectoire opposable (avec A12) | T50: 3 | U50: Perçu +4 par tour sur le bloc jusqu'à la fin de la partie. Révèle la capture de subvention. | V50: Ne décide rien, mais rend l'écart entre annonces et actes publiquement mesurable à chaque tour. | W50: Committee on Climate Change britannique (2008) ; Haut Conseil pour le Climat français (2019). | X50: Un rapport annuel ignoré reste un rapport annuel. Son pouvoir dépend entièrement de la reprise médiatique. | Y50: Noyau · Coalition — rend l'inaction publiquement mesurable à chaque tour
A51: A64 | B51: Actif | C51: Électoral | D51: Constitutionnalisation de l'objectif climat | E51: graver dans le marbre | F51: Bloc | G51: 5 | J51: 2 | K51: 55 | L51: 3 | M51: une loi-cadre déjà en vigueur quelque part — on ne constitutionnalise pas à froid | N51: 40 | O51: Irréversible | P51: Élevée | Q51: T28 | T51: 5 | U51: Dans deux tours : le bloc est protégé définitivement et gagne 8 de contrainte. Deux chances sur cinq d'aboutir. | V51: Inscrire l'objectif au niveau constitutionnel place la mesure hors de portée d'une majorité ordinaire. C'est le seul verrou du jeu qu'une alternance ne défait pas. | W51: Projet de révision constitutionnelle française sur la préservation de l'environnement, adopté par l'Assemblée en 2021 puis abandonné faute d'accord au Sénat. | X51: Coût politique maximal et échec fréquent : la procédure exige une majorité qualifiée ou un référendum, et l'échec consomme tout le capital engagé. | Y51: Extension · niveau Expert, coût politique maximal, échec fréquent
A52: A65 | B52: Actif | C52: International | D52: Accord multilatéral à cliquet | E52: diplomatie sans effet | F52: Mondial | G52: 4 | J52: 2 | L52: 3 | M52: un protocole sectoriel, ou trois blocs déjà contraints à 20 | N52: 100 | O52: Difficile à annuler | P52: Élevée | Q52: T64 | S52: Confiance multilatérale (avec A29) · Le club et le cliquet (avec A66) | T52: 4 | U52: Contrainte +4 partout dans deux tours, puis +2 par tour ensuite. Aucun effet immédiat. | V52: Ne réduit rien directement : installe un mécanisme de révision périodique qui rend le recul coûteux en réputation. | W52: Accord de Paris, décembre 2015 — le point de départ de cette partie. Trajectoire mondiale passée de 3,6 °C à 2,6 °C entre 2015 et 2025. | X52: Aucune sanction. Tout repose sur la transparence et la pression des pairs. | Y52: Obligatoire · International — c'est le tour 1 de la partie (Paris, décembre 2015)
A53: A66 | B53: Actif | C53: International | D53: Coalition de volontaires | E53: club des vertueux | F53: Mondial | G53: 3 | H53: 2 | J53: 1 | L53: 2 | M53: trois blocs déjà contraints à 15 — une coalition réunit ceux qui agissaient déjà | N53: 74 | O53: Difficile à annuler | P53: Moyenne | Q53: T18 | S53: Le club et le cliquet (avec A65) | T53: 3 | U53: Contrainte +5 au tour suivant sur les quatre blocs déjà les plus contraints. Ne dépend d'aucun consensus. | V53: Plutôt que d'attendre l'unanimité, réunir ceux qui sont prêts et fixer la norme entre eux. Le club devient le standard, et les autres le rejoignent par intérêt commercial. | W53: Powering Past Coal Alliance, 2017 ; Beyond Oil and Gas Alliance, 2021 ; alliances sur le méthane depuis 2021. | X53: Une coalition de volontaires réunit ceux qui agissaient déjà. Elle ne touche pas les blocs qui décident du total. | Y53: Extension · contourne l'unanimité ; réintégrer si la couche internationale est trop pauvre
A54: A67 | B54: Actif | C54: International | D54: Protocole sectoriel contraignant | E54: abandon de souveraineté | F54: Mondial | G54: 4 | J54: 1 | L54: 3 | N54: 58 | O54: Irréversible | P54: Élevée | Q54: T44 | R54: oui | S54: Le coup de Kigali (avec A11) | T54: 5 | U54: Contrainte +11 partout au tour suivant. Irréversible. | V54: Le format qui a le mieux fonctionné à ce jour : cible étroite, substitut disponible, calendrier daté, sanctions commerciales. | W54: Amendement de Kigali au Protocole de Montréal (2016) sur les HFC : jusqu'à 0,4 °C évités à lui seul. | X54: Ne fonctionne que sur des gaz ou secteurs à substitut existant. Inapplicable au CO₂ énergétique. | Y54: Noyau · International — le format le plus efficace jamais signé (Kigali 2016)
A55: A70 | B55: Actif | C55: Judiciaire | D55: Contentieux en responsabilité fondé sur l'attribution | E55: faire payer les dégâts | F55: Bloc | G55: 3 | H55: 2 | J55: 2 | L55: 3 | M55: une attribution rapide ou un contentieux national déjà engagé | N55: 48 | O55: Irréversible | P55: Moyenne | Q55: T28 | T55: 3 | U55: Contrainte +16 dans deux tours sur le bloc, et crédibilité adverse −10. Une chance sur deux d'aboutir. | V55: La science d'attribution permet de rattacher un événement précis à une part d'émissions précise. La responsabilité cesse d'être diffuse et devient chiffrable devant un juge civil. | W55: Lliuya c. RWE, procédure allemande ouverte en 2015 sur la fonte d'un glacier péruvien ; essor des études d'attribution rapide depuis 2015. | X55: Levier émergent : les décisions favorables sont rares, souvent infirmées en appel, et la causalité individuelle reste le point d'attaque le plus solide de la défense. | Y55: Extension · niveau Expert. Couple très bien avec A49 (attribution) — réintégrer si le noyau juridique se révèle mince
A56: A71 | B56: Actif | C56: International | D56: Dénonciation du traité sur la Charte de l'énergie | E56: claquer la porte | F56: Mondial | G56: 4 | J56: 1 | L56: 3 | M56: un arbitrage déjà subi, ou un avis consultatif déjà obtenu | N56: 58 | O56: Irréversible | P56: Élevée | S56: La sortie par le droit (avec A36) | U56: Neutralise définitivement l'arbitrage investisseur-État : la protection des investissements devient injouable pour le reste de la partie. | V56: Tant que le traité s'applique, toute sortie du fossile expose l'État à une réclamation devant un tribunal privé. Le dénoncer ne supprime pas les contentieux en cours, il ferme la porte aux suivants. | W56: Retraits du traité sur la Charte de l'énergie annoncés par la France, l'Allemagne et l'Espagne en 2022-2023, puis retrait coordonné de l'Union européenne acté en 2024. | X56: La clause de survie protège les investissements existants pendant vingt ans : ce que le traité couvrait déjà reste couvert.
A57: A72 | B57: Actif | C57: Réglementaire | D57: Fin des nouvelles licences d'exploration | E57: fermer le robinet | F57: Bloc | G57: 3 | K57: 45 | L57: 2 | M57: un plafond déjà abaissé par l'adversaire — sinon il n'y a rien à rouvrir | N57: 100 | O57: Difficile à annuler | P57: Élevée | Q57: T40 | U57: Plafond de contrainte +12 sur le bloc, sans dépasser 100, et contrainte +4. Défait le verrouillage par l'infrastructure. | V57: On n'agit pas sur ce qui est déjà en production mais sur ce qui ne l'est pas encore. Chaque licence non délivrée est un actif de trente ans qui n'existera pas. | W57: Danemark : arrêt des nouvelles licences en mer du Nord voté en décembre 2020 avec échéance 2050 ; engagements comparables au sein de la Beyond Oil and Gas Alliance. | X57: Aucun effet sur les émissions du tour : le levier agit sur ce qui aurait été extrait dans vingt ans. C'est un plafond qu'on relève, pas une contrainte qu'on ajoute.
A58: A73 | B58: Actif | C58: Économique | D58: Fin du financement public à l'export des fossiles | E58: couper le crédit | F58: Mondial | G58: 4 | L58: 2 | N58: 72 | O58: Difficile à annuler | P58: Élevée | Q58: T46 | T58: 3 | U58: Contrainte +8 sur les cinq blocs à rente fossile élevée. Réduite de moitié si les actifs sales ont déjà été cédés — le projet a simplement changé de porteur. | V58: Les agences de crédit à l'export garantissent ce que le marché ne garantirait pas. Retirer la garantie ne rend pas le projet illégal, elle le rend impayable — tant qu'aucun autre État ne la reprend. | W58: Déclaration de Glasgow sur le soutien public à l'énergie propre, COP26 décembre 2021 : environ 39 signataires s'engagent à cesser le financement à l'export des fossiles non abattus. | X58: Un financeur non signataire reprend le dossier. C'est le seul levier du jeu dont l'efficacité dépend entièrement du nombre de blocs qui l'ont déjà joué. | Y58: Extension · contré par T46 (cession d'actifs) — tester si la paire fonctionne
A59: T01 | B59: Attentiste | C59: Discours | D59: Responsabilité individuelle | E59: individualisation du problème | F59: Bloc | I59: 2 | L59: 1 | N59: 100 | O59: Facile à annuler | P59: Élevée | Q59: A50 | S59: Chacun sa part (avec T31) | T59: 4 | U59: Perçu −9. Déplace la cible de la production vers le consommateur. | V59: Chacun décide de ses trajets, de son chauffage, de son assiette. Rendre ces choix visibles est plus rapide, moins coûteux et moins clivant qu'une contrainte imposée d'en haut. | W59: Calculateur d'empreinte carbone individuelle lancé par BP en 2004, aujourd'hui universel. | X59: L'empreinte carbone individuelle a été popularisée par une campagne de BP en 2004. Les gestes individuels sans changement d'infrastructure plafonnent autour d'un quart de l'empreinte d'un ménage : l'essentiel dépend de choix collectifs. L'argument se retourne quand le soutien réel de la population est publié. | Y59: Noyau · Discours — déplace la cible de la production vers le consommateur (BP, 2004)
A60: T02 | B60: Attentiste | C60: Discours | D60: Conditionner l'effort aux autres | E60: whataboutisme | F60: Bloc | I60: 1 | L60: 1 | N60: 100 | O60: Facile à annuler | P60: Élevée | Q60: A03 | T60: 4 | U60: Perçu −13 si le bloc pèse moins de 10 % des émissions mondiales, −5 sinon. | V60: Un bloc qui pèse 2 % des émissions mondiales ne change pas la trajectoire à lui seul. Demander que les gros émetteurs bougent d'abord est une exigence de réciprocité, pas un refus d'agir. | W60: Argument central des débats parlementaires français et européens sur toute mesure contraignante. | X60: L'argument est symétrique : si chacun attend l'autre, personne ne bouge. Il perd sa force face à un ajustement carbone aux frontières, qui rend l'effort conditionnel visible, et face au financement Nord-Sud, qui lève l'objection de capacité. | Y60: Noyau · Discours — annule une mesure dans un bloc à faibles émissions relatives
A61: T04 | B61: Attentiste | C61: Discours | D61: Confiance dans l'innovation | E61: optimisme technologique de report | F61: Mondial | I61: 2 | L61: 1 | N61: 100 | O61: Facile à annuler | P61: Élevée | Q61: A39 | S61: La promesse sans date (avec T07) | T61: 4 | U61: Perçu −5 partout, et les effets différés du camp actif sont retardés d'un tour. | V61: Le coût du solaire a baissé de 90 % en dix ans sans qu'on l'ait décrété. Engager aujourd'hui des sommes considérables dans des technologies qui seront obsolètes dans quinze ans est un mauvais calcul. | W61: Promesses successives sur la fusion, le captage direct dans l'air, l'hydrogène généralisé. | X61: L'argument vaut pour les technologies qui existent déjà et se déploient. Il devient un report quand il s'appuie sur des technologies non démontrées à l'échelle : fusion, captage direct dans l'air, hydrogène généralisé. Le budget carbone, lui, se dépense chaque année pendant l'attente. | Y61: Noyau · Discours — reporte la décision de N tours contre une promesse future
A62: T05 | B62: Attentiste | C62: Économique | D62: Le gaz comme énergie de transition | E62: verrouillage gazier | F62: Bloc | H62: 3 | L62: 1 | N62: 100 | O62: Difficile à annuler | P62: Élevée | Q62: A21 | T62: 5 | U62: Contrainte −9 et plafond −6 : du fossile financé sur budget climat. | V62: Le gaz émet à la combustion moitié moins que le charbon et fournit l'équilibrage dont un réseau très renouvelable a besoin. Substituer le gaz au charbon est un gain immédiat. | W62: Classement du gaz dans la taxonomie verte européenne, 2022. Fuites de méthane amont qui annulent une large part du gain affiché. | X62: Le gain à la combustion est réel ; les fuites de méthane en amont en annulent une part importante, et l'infrastructure construite engage quarante ans. Le classement du gaz dans la taxonomie verte européenne date de 2022. Le renforcement du réseau et du stockage supprime l'argument de l'équilibrage. | Y62: Noyau · Discours — fait financer du fossile sur budget climat (puissance 5)
A63: T07 | B63: Attentiste | C63: Discours | D63: Engagement de long terme | E63: objectif net zéro sans trajectoire | F63: Mondial | I63: 2 | L63: 1 | N63: 100 | O63: Facile à annuler | P63: Élevée | Q63: A63 | S63: La promesse sans date (avec T04) | T63: 5 | U63: Perçu +6 partout pour le camp attentiste, sans aucune réduction. Sans effet si une institution de suivi existe. | V63: Un objectif à trente ans donne aux entreprises la visibilité nécessaire pour investir, sans imposer de rupture brutale à une économie qui a besoin de temps pour s'adapter. | W63: Prolifération des engagements net zéro 2050 sans trajectoire 2030 opposable. | X63: Les engagements net zéro 2050 se sont généralisés sans que les trajectoires 2030 suivent. Un objectif sans étape intermédiaire n'engage aucun décideur en exercice. Une institution indépendante de suivi transforme l'annonce en dette publiquement mesurée chaque année. | Y63: Noyau · Discours — marque des points d'opinion sans réduire une tonne (puissance 5)
A64: T08 | B64: Attentiste | C64: Discours | D64: Défense des ménages modestes | E64: instrumentalisation sociale | F64: Bloc | I64: 2 | L64: 1 | N64: 100 | O64: Facile à annuler | P64: Élevée | Q64: A31 | T64: 5 | U64: Friction +19. Effet réduit des deux tiers si la redistribution a été installée. | V64: Une taxe sur l'énergie frappe proportionnellement plus fort les bas revenus, les ruraux et ceux qui n'ont pas le choix de leur mode de chauffage ou de transport. L'objection est fondée. | W64: Argumentaire déployé contre les zones à faibles émissions et contre toute tarification non redistribuée. | X64: Elle est fondée tant que rien n'est rendu. Le dividende carbone canadien rend davantage aux ménages modestes qu'il ne leur coûte, et n'a jamais été renversé. Face à une redistribution visible, l'argument perd les deux tiers de sa force. | Y64: Noyau · Discours — retourne l'argument social. Dévastateur si A31 n'a pas été joué
A65: T09 | B65: Attentiste | C65: Discours | D65: Défense du mode de vie | E65: défense identitaire du statu quo | F65: Bloc | I65: 2 | L65: 1 | N65: 100 | O65: Difficile à annuler | P65: Élevée | Q65: A57 | T65: 4 | U65: Soutien réel −4 et friction +12. Attaque le réel, pas seulement le perçu. | V65: La voiture, la viande, le départ en vacances ne sont pas des caprices : ce sont les marqueurs d'une vie normale que des générations ont mis un siècle à conquérir. Les remettre en cause a un coût politique réel. | W65: Polémiques récurrentes sur la viande, l'avion et la voiture individuelle depuis 2019. | X65: L'argument attaque le soutien de fond, pas seulement la perception — c'est ce qui le rend redoutable. Il s'affaiblit face à un récit de gain plutôt que de privation, à condition que ce récit précède l'attaque et que les mesures effectivement prises ne le démentent pas. | Y65: Noyau · Discours — attaque le soutien RÉEL et non le perçu : mécaniquement distinct des autres discours
A66: T10 | B66: Attentiste | C66: Discours | D66: Whataboutisme des inconvénients | E66: et le cobalt ? | F66: Bloc | H66: 2 | L66: 1 | N66: 100 | O66: Facile à annuler | P66: Élevée | Q66: A54 | T66: 3 | U66: Indice technologique −5 et perçu −7 sur le bloc. Perçu −11 dès que l'indice dépasse 30 : plus la technologie est visible, plus elle offre de prise. | V66: Ne pas défendre le fossile, attaquer l'alternative. Mines de cobalt, terres rares, oiseaux, recyclage des pales : chaque objection est fondée prise isolément, et aucune n'est mise en regard de ce qu'elle remplace. | W66: Campagnes sur les conditions d'extraction du cobalt et sur l'impact des éoliennes, relayées à partir de 2015 par des organisations sans activité documentée sur les mêmes sujets ailleurs. | X66: L'argument ne tient que tant que la comparaison n'est pas faite. Un travail d'enquête qui met les deux bilans côte à côte le retourne entièrement. | Y66: Extension · bloque une technologie de substitution sans défendre le fossile : mécaniquement intéressant
A67: T11 | B67: Attentiste | C67: Discours | D67: Réalisme sur les délais | E67: fatalisme démobilisateur | F67: Bloc | I67: 2 | L67: 2 | N67: 100 | O67: Facile à annuler | P67: Élevée | Q67: A51 | T67: 4 | U67: Perçu −10, et −16 dès que le réchauffement dépasse 1,6 °C. | V67: Regarder les chiffres en face : le budget 1,5 °C est presque épuisé, les émissions mondiales n'ont pas encore baissé. Promettre l'inverse entretient une illusion qui se paiera en désillusion. | W67: Montée documentée de l'éco-anxiété résignée chez les moins de 25 ans depuis 2020. | X67: Le constat est exact, la conclusion ne l'est pas : chaque dixième de degré évité compte, et la trajectoire mondiale est passée de 3,6 °C à 2,6 °C entre 2015 et 2025. Le levier se renforce mécaniquement quand la partie se dégrade — c'est pourquoi montrer ce qui a marché est le seul contre efficace. | Y67: Signature · Discours — puissance croissante avec la température. Le seul levier qui se renforce quand la partie se dégrade
A68: T13 | B68: Attentiste | C68: Institutionnel | D68: Représentation d'intérêts | E68: lobbying d'obstruction | F68: Bloc | H68: 3 | L68: 1 | N68: 100 | O68: Facile à annuler | P68: Élevée | Q68: A15 | T68: 4 | U68: Friction +13 et contrainte −5. | V68: Les secteurs concernés connaissent leurs contraintes techniques mieux que le législateur. Intervenir dans l'écriture du texte, avant le vote, évite des normes inapplicables. | W68: InfluenceMap : plusieurs centaines de millions de dollars par an d'influence climatique obstructive documentée. | X68: InfluenceMap documente plusieurs centaines de millions de dollars par an d'influence climatique obstructive, avec un rapport coût/effet sans équivalent. Les registres de transparence et le reporting obligatoire en réduisent le rendement sans le supprimer. | Y68: Noyau · Institutionnel — la base du camp, disponible dès le niveau Découverte
A69: T17 | B69: Attentiste | C69: Institutionnel | D69: Allègement du contrôle | E69: capture de l'agence réglementaire | F69: Bloc | H69: 4 | L69: 3 | N69: 66 | O69: Difficile à annuler | P69: Élevée | Q69: A12 | T69: 5 | U69: Contrainte −17. Sans effet sur un bloc verrouillé par une loi-cadre. | V69: Une autorité de contrôle surdimensionnée coûte cher et ralentit les projets. Recentrer ses moyens sur ses missions essentielles est une bonne gestion des finances publiques. | W69: Sous-dotation chronique des autorités de contrôle environnemental dans plusieurs blocs. | X69: Le résultat est que la norme reste au Journal officiel et cesse d'être appliquée. C'est moins visible qu'une abrogation, donc moins coûteux politiquement. Une loi-cadre avec budget carbone opposable rend le sous-contrôle attaquable en justice. | Y69: Pilier · Institutionnel — le vote reste, l'effet disparaît. Mécanique unique et brutale
A70: T18 | B70: Attentiste | C70: International | D70: Occupation des négociations internationales | E70: délégation élargie | F70: Mondial | H70: 2 | L70: 2 | N70: 100 | O70: Facile à annuler | P70: Élevée | Q70: A66 | T70: 3 | U70: Chaque effet différé en attente perd 3 de contrainte, et le prochain sommet international reste sans effet. | V70: Il n'est pas nécessaire de bloquer : il suffit d'être assez nombreux dans la salle pour que chaque formulation soit négociée jusqu'à ne plus rien exiger. | W70: Plus de 2 400 personnes affiliées aux énergies fossiles accréditées à la COP28, 2023 — davantage que la quasi-totalité des délégations nationales. | X70: On dilue un texte en préparation, pas un texte déjà entré en vigueur. | Y70: Extension · portée mondiale à coût faible ; réintégrer avec la couche internationale
A71: T19 | B71: Attentiste | C71: Institutionnel | D71: Harmonisation nationale | E71: préemption législative | F71: Bloc | G71: 3 | L71: 2 | N71: 72 | O71: Difficile à annuler | P71: Élevée | Q71: A61 | S71: Verrou administratif (avec T20) | T71: 5 | U71: Le camp actif ne peut plus jouer sur ce bloc pendant deux tours, sauf par l'échelon local. | V71: Un patchwork de règles locales fragmente le marché intérieur et crée une insécurité juridique pour les entreprises. Fixer la règle au niveau national est un principe d'égalité devant la loi. | W71: Plus de vingt États américains interdisant à leurs villes de bannir le gaz depuis 2020. | X71: Plus de vingt États américains interdisent depuis 2020 à leurs villes de bannir le gaz. L'harmonisation retire l'échelon où les majorités climatiques sont les plus solides. Les réseaux de villes internationaux contournent partiellement le blocage. | Y71: Noyau · Institutionnel — annule d'un coup toutes les cartes locales adverses (contre A61)
A72: T20 | B72: Attentiste | C72: Institutionnel | D72: Simplification normative | E72: détricotage administratif | F72: Bloc | H72: 3 | L72: 3 | M72: au moins cinq mesures adverses en vigueur — il faut un stock à simplifier | N72: 70 | O72: Facile à annuler | P72: Élevée | Q72: A12 | S72: Verrou administratif (avec T19) | T72: 5 | U72: Contrainte −14 et plafond −6. Passe sous le radar médiatique. | V72: Alléger des obligations de reporting devenues illisibles rend du temps et de l'argent aux entreprises, en particulier aux plus petites. Personne ne défend la complexité pour elle-même. | W72: Paquet omnibus européen de 2025, réduisant fortement le périmètre de CSRD et CSDDD. | X72: Le paquet omnibus européen de 2025 a fortement réduit le périmètre de CSRD et CSDDD. Vider une norme par simplification ne mobilise personne, contrairement à une abrogation. Inopérant contre une mesure inscrite dans une trajectoire opposable. | Y72: Pilier · Institutionnel — vide une norme par simplification, sous le radar médiatique (omnibus UE 2025)
A73: T21 | B73: Attentiste | C73: Institutionnel | D73: Concertation approfondie | E73: obstruction procédurale | F73: Bloc | G73: 2 | L73: 2 | N73: 100 | O73: Facile à annuler | P73: Élevée | Q73: A12 | T73: 4 | U73: Tous les effets différés en cours sur ce bloc sont retardés de deux tours. | V73: Une réglementation mal préparée se fait annuler et fait perdre des années. Prendre le temps de la consultation et de l'étude d'impact est la condition de sa solidité juridique. | W73: Multiplication des phases de concertation préalable sur les projets réglementaires. | X73: L'argument ne s'oppose jamais publiquement au fond — c'est ce qui le rend difficile à combattre. Multiplier les phases repousse l'entrée en vigueur sans qu'aucun vote défavorable n'ait lieu. Des échéances datées dans la loi rendent le report juridiquement attaquable. | Y73: Noyau · Institutionnel — PROMU : report de 2 à 3 tours sans jamais s'opposer publiquement. Contre de A63
A74: T22 | B74: Attentiste | C74: Institutionnel | D74: Adaptation sectorielle | E74: exemption négociée | F74: Bloc | H74: 3 | L74: 1 | N74: 100 | O74: Difficile à annuler | P74: Élevée | Q74: A12 | T74: 5 | U74: Contrainte −12. Sans effet si le bloc est verrouillé. | V74: Certains secteurs n'ont pas d'alternative technique disponible. Les soumettre à la règle générale ne réduit rien et détruit de la valeur : l'exception est une mesure de bon sens. | W74: Aviation et maritime longtemps hors ETS ; dérogations agricoles obtenues en 2024. | X74: L'aviation et le maritime sont restés longtemps hors ETS, les dérogations agricoles ont été obtenues en 2024. Chaque exemption affaiblit la crédibilité du texte et en appelle d'autres. Sans effet sur un bloc verrouillé par une loi-cadre. | Y74: Noyau · Institutionnel — la mesure passe, le secteur clé en sort (puissance 5)
A75: T23 | B75: Attentiste | C75: Institutionnel | D75: Clause de réexamen | E75: annulation programmée | F75: Bloc | G75: 1 | L75: 2 | M75: au moins deux mesures adverses en vigueur, dans lesquelles insérer la clause | N75: 100 | O75: Facile à annuler | P75: Élevée | Q75: A62 | T75: 4 | U75: Programme l'annulation d'une mesure du bloc dans trois tours. | V75: Une trajectoire fixée pour dix ans doit pouvoir être ajustée si la technologie ou le contexte économique changent. Prévoir un rendez-vous est de la bonne législation. | W75: Clause de réexamen 2026 inscrite dans le règlement européen de fin du thermique en 2035. | X75: Insérer une révision datée coûte presque rien au moment du vote et rouvre tout au moment choisi. Le règlement européen de fin du thermique en 2035 comporte une clause de réexamen en 2026. Un accord transpartisan retire la revoyure du jeu politique ordinaire. | Y75: Signature · Institutionnel — fenêtre d'annulation programmée au tour n+3. Mécaniquement très élégant
A76: T24 | B76: Attentiste | C76: Judiciaire | D76: Protection des investissements | E76: arbitrage investisseur-État | F76: Mondial | H76: 4 | L76: 3 | M76: au moins trois mesures adverses en vigueur | N76: 60 | O76: Difficile à annuler | P76: Élevée | Q76: A71 | T76: 4 | U76: Contrainte −8 sur les deux blocs les plus contraints. Sans effet si un avis international a été rendu. | V76: Un investisseur qui a engagé des milliards sur la foi d'un cadre juridique doit pouvoir être indemnisé si l'État change ce cadre. C'est le principe de sécurité juridique. | W76: RWE et Uniper contre Pays-Bas (environ 1,4 Md€) ; Rockhopper contre Italie (190 M€), via le Traité sur la Charte de l'énergie. | X76: RWE et Uniper ont réclamé environ 1,4 Md€ aux Pays-Bas, Rockhopper 190 M€ à l'Italie, via le Traité sur la Charte de l'énergie. L'effet dissuasif dépasse largement les cas jugés. Les retraits du Traité depuis 2023 réduisent le terrain de jeu. | Y76: Noyau · Judiciaire — fait payer à l'État le coût de sa propre politique. Effet dissuasif au-delà du cas jugé
A77: T25 | B77: Attentiste | C77: Judiciaire | D77: Recours en légalité | E77: contentieux dilatoire | F77: Bloc | H77: 3 | L77: 1 | M77: au moins deux mesures adverses en vigueur — sans texte, pas de recours | N77: 76 | O77: Facile à annuler | P77: Élevée | Q77: A33 | T77: 4 | U77: Suspend la dernière mesure du bloc : contrainte −10 au plus, −4 si le bloc n'a aucune mesure. | V77: Une norme entachée d'un vice de procédure ou disproportionnée doit pouvoir être contestée. Le recours est un droit, pas une manœuvre. | W77: Contentieux systématiques contre les réglementations environnementales fédérales américaines. | X77: Gagner n'est pas nécessaire : trois à cinq ans de suspension suffisent. Les réglementations environnementales fédérales américaines font l'objet de recours quasi systématiques. Sans effet sur les mesures adossées à une obligation juridictionnelle supérieure. | Y77: Noyau · Judiciaire — gagner n'est pas nécessaire, retarder suffit. Niveau Découverte
A78: T26 | B78: Attentiste | C78: Judiciaire | D78: Action en diffamation | E78: procédure-bâillon | F78: Bloc | H78: 3 | L78: 3 | M78: au moins trois mesures adverses en vigueur | N78: 68 | O78: Difficile à annuler | P78: Élevée | Q78: A54 | T78: 3 | U78: Le camp actif perd 1 point d'Attention pendant deux tours. | V78: Une accusation publique infondée cause un préjudice réel. Saisir le juge est la voie normale pour le faire constater. | W78: Poursuites contre des ONG environnementales en Europe et aux États-Unis ; directive européenne anti-SLAPP de 2024. | X78: Le déséquilibre de moyens fait l'effet : une ONG ou un journaliste indépendant s'épuise financièrement avant le jugement, quelle que soit l'issue. La directive européenne anti-SLAPP de 2024 rend la procédure risquée pour son auteur dans les blocs européens. | Y78: Noyau · Judiciaire — supprime une source d'attribution adverse (contre A54 et A49)
A79: T27 | B79: Attentiste | C79: Judiciaire | D79: Criminalisation de la contestation | E79: maintien de l'ordre | F79: Bloc | H79: 3 | L79: 3 | M79: une contestation à réprimer : une désobéissance civile jouée, ou un bloc à 40 de friction | N79: 70 | O79: Difficile à annuler | P79: Élevée | Q79: A52 | T79: 3 | U79: La friction du bloc retombe de 12 et la désobéissance civile y devient injouable pour le reste de la partie. Crédibilité adverse −6. | V79: Alourdir les peines pour blocage d'infrastructure ne vise pas l'opinion mais la capacité d'action. Le mouvement ne se tait pas, il devient trop coûteux à rejoindre. | W79: Alourdissement des peines pour perturbation d'infrastructures au Royaume-Uni à partir de 2022 ; peines de prison ferme prononcées contre des militants climatiques en 2023-2024. | X79: Réprimer un mouvement le rend plus visible qu'il ne l'était. La friction retombe, mais le soutien réel déjà acquis reste acquis. | Y79: Extension · transforme A52 en handicap — réintégrer si A52 entre dans le noyau
A80: T28 | B80: Attentiste | C80: Judiciaire | D80: Attaque constitutionnelle de la mesure | E80: le vice de forme | F80: Bloc | H80: 3 | L80: 3 | M80: une mesure adverse à faire censurer | N80: 62 | O80: Irréversible | P80: Élevée | Q80: A70 | T80: 4 | U80: Fait tomber la dernière mesure du bloc sur un motif de forme : la contrainte perd la valeur de cette mesure, la loi-cadre saute, et plus aucune ne peut être reposée ici. | V80: On n'attaque pas le fond, qui se défend bien, mais la procédure, l'égalité devant les charges ou la compétence du législateur. La censure crée un précédent qui vaut interdiction. | W80: Censures constitutionnelles de dispositions fiscales environnementales, notamment la contribution carbone française annulée en décembre 2009 pour rupture d'égalité. | X80: Le précédent protège aussi l'adversaire : il fixe ce qui est censurable, donc ce qui ne l'est pas. Un texte réécrit en tenant compte de la censure passe ensuite sans obstacle. | Y80: Extension · irréversible et crée un précédent : puissant, à équilibrer avec soin
A81: T30 | B81: Attentiste | C81: Narratif | D81: Astroturfing | E81: collectif de riverains | F81: Bloc | H81: 2 | I81: 1 | L81: 1 | N81: 100 | O81: Facile à annuler | P81: Élevée | Q81: A50 | T81: 4 | U81: Perçu −12 sans toucher au soutien réel : l'écart entre ce que le bloc pense et ce qu'il paraît penser se creuse d'autant. | V81: Fabriquer l'apparence d'une opposition locale spontanée coûte moins cher que de convaincre. L'élu ne mesure pas l'opinion, il mesure le bruit. | W81: Collectifs anti-éoliens à financement opaque ; campagnes de courriers pré-remplis adressés aux élus locaux. | X81: Le soutien réel reste intact dessous. Un levier de révélation le rattrape d'un coup, et l'astroturf apparaît alors pour ce qu'il est. | Y81: Extension · fait chuter le perçu sans toucher au réel : très bon candidat au noyau en seconde vague
A82: T31 | B82: Attentiste | C82: Narratif | D82: Communication sur les engagements | E82: greenwashing | F82: Bloc | H82: 3 | L82: 1 | N82: 100 | O82: Facile à annuler | P82: Moyenne | Q82: A37 | S82: Chacun sa part (avec T01) | T82: 3 | U82: Perçu −11 pour le camp actif : le sentiment que le problème est déjà traité. | V82: Une entreprise qui investit dans la transition a le droit de le faire savoir. La communication est aussi ce qui rend la transition désirable auprès du public. | W82: Campagnes des majors sur leurs investissements bas carbone, souvent inférieurs à 5 % de leurs dépenses d'investissement. | X82: Les campagnes des majors portent souvent sur des investissements bas carbone inférieurs à 5 % de leurs dépenses d'investissement. L'effet sur l'opinion est le sentiment que le problème est déjà traité. Vulnérable au contentieux publicitaire et à l'interdiction de publicité fossile. | Y82: Noyau · Narratif — achète du soutien perçu sans réduire d'émissions
A83: T33 | B83: Attentiste | C83: Narratif | D83: Investissement dans les médias | E83: concentration médiatique | F83: Bloc | H83: 5 | L83: 3 | N83: 100 | O83: Difficile à annuler | P83: Élevée | Q83: A37 | T83: 5 | U83: Perçu −7 sur le bloc à chaque tour jusqu'à la fin de la partie. | V83: La presse perd de l'argent. Des actionnaires qui la recapitalisent la maintiennent en vie ; l'indépendance des rédactions est garantie par leur statut. | W83: Concentration croissante de la propriété des médias d'information dans plusieurs blocs depuis 2015. | X83: C'est le seul levier vraiment cumulatif du camp : il convertit du capital en influence durable sur l'attention. Cher, lent et très visible, il expose à l'investigation et au débat public sur la concentration. | Y83: Pilier · Narratif — convertit du capital en contrôle durable de l'attention (puissance 5)
A84: T36 | B84: Attentiste | C84: Narratif | D84: Maîtrise du calendrier | E84: saturation de l'attention | F84: Mondial | H84: 3 | L84: 1 | N84: 100 | O84: Facile à annuler | P84: Élevée | Q84: A49 | T84: 4 | U84: Aucune attribution d'événement possible ce tour-ci. | V84: Communiquer au bon moment fait partie du métier. Publier un rapport technique en pleine actualité chargée n'est pas une faute, c'est un arbitrage. | W84: Pratique documentée de publication des rapports défavorables les veilles de week-end et de grands événements. | X84: La pratique est documentée : les publications défavorables sortent les veilles de week-end et de grands événements. Une équipe d'attribution rapide publie avant la fenêtre de saturation. | Y84: Pilier · Narratif — contre direct de A49 : aucune attribution possible ce tour-ci
A85: T38 | B85: Attentiste | C85: Narratif | D85: Bataille des valeurs | E85: polarisation identitaire | F85: Bloc | I85: 4 | L85: 2 | N85: 70 | O85: Irréversible | P85: Élevée | T85: 5 | U85: Perçu −12 et dépolitisation rendue impossible sur ce bloc pour toute la partie. | V85: L'écologie porte un projet de société qui ne dit pas son nom. Le nommer et le contester ouvertement est un débat démocratique légitime. | W85: Polarisation partisane croissante du sujet climatique depuis 2010, mesurée dans plusieurs démocraties. | X85: La polarisation partisane du climat est mesurée dans plusieurs démocraties depuis 2010. Une fois installée, elle ferme durablement la voie de l'accord transpartisan — y compris pour son auteur, qui perd aussi la possibilité du compromis. | Y85: Pilier · Narratif — irréversible, rend A62 (dépolitisation) impossible pour le reste de la partie
A86: T39 | B86: Attentiste | C86: Narratif | D86: Défense du pouvoir d'achat | E86: instrumentalisation du coût de la vie | F86: Bloc | I86: 2 | L86: 1 | N86: 100 | O86: Facile à annuler | P86: Élevée | Q86: A31 | S86: Colère ciblée (avec T41) | T86: 5 | U86: Friction +24. Divisée par deux si la redistribution est installée, encore réduite si la coalition élargie existe. | V86: Une hausse du prix de l'énergie tombe immédiatement sur des ménages sans marge. Le rappeler au moment où la facture arrive n'est pas de la manipulation, c'est de la représentation. | W86: Crise énergétique de 2022 ; retournement du discours européen sur le Pacte vert dans la foulée. | X86: C'est le levier numéro un du camp depuis la crise énergétique de 2022, et il a suffi à retourner le discours européen sur le Pacte vert. Il perd la moitié de sa force face à une compensation visible, davantage encore face à une coalition qui inclut le pouvoir d'achat dès le départ. | Y86: Pilier · Narratif — levier numéro un depuis 2022. Convertit toute mesure non compensée en friction maximale
A87: T40 | B87: Attentiste | C87: Narratif | D87: Sécurité d'approvisionnement | E87: instrumentalisation de la crise énergétique | F87: Bloc | I87: 2 | L87: 1 | N87: 100 | O87: Difficile à annuler | P87: Élevée | Q87: A72 | T87: 5 | U87: Plafond −10 : des projets fossiles rouverts au nom de la souveraineté. | V87: Un pays qui ne peut plus se chauffer ni produire n'a plus de politique climatique du tout. Sécuriser l'approvisionnement est un préalable, pas une alternative. | W87: Relance des terminaux GNL européens après 2022 ; réouverture temporaire de centrales à charbon. | X87: La peur de la coupure a autorisé en quelques semaines, après 2022, ce qu'aucun débat n'aurait accordé en dix ans : terminaux GNL, réouvertures de centrales. Le renforcement du réseau et du stockage retire l'argument de la fragilité. | Y87: Noyau · Narratif — rouvre les projets fossiles au nom de la souveraineté. Lié aux cartes géopolitiques
A88: T41 | B88: Attentiste | C88: Narratif | D88: Écoute des territoires | E88: fracturation de la coalition | F88: Bloc | I88: 3 | L88: 1 | N88: 100 | O88: Difficile à annuler | P88: Élevée | Q88: A60 | S88: Colère ciblée (avec T39) | T88: 5 | U88: Friction +17 et perçu −6. Effet doublé si le bloc a subi une mesure agricole ou nucléaire. | V88: Agriculteurs, automobilistes, ruraux, salariés d'un site industriel : ces gens subissent la transition sans l'avoir décidée. Porter leur voix est le rôle d'un représentant. | W88: Mobilisations agricoles européennes de 2024 ; Gilets jaunes de 2018. | X88: Détacher un groupe social coûte beaucoup moins cher que convaincre l'ensemble de la population — les mobilisations agricoles de 2024 et les Gilets jaunes de 2018 l'ont montré. Une coalition construite dès le départ sur l'emploi et le pouvoir d'achat offre peu de prise. | Y88: Pilier · Narratif — détache un groupe social de la coalition adverse (contre A60)
A89: T43 | B89: Attentiste | C89: Économique | D89: Investissement d'infrastructure | E89: verrouillage carbone | F89: Bloc | H89: 5 | L89: 1 | N89: 100 | O89: Irréversible | P89: Élevée | Q89: A72 | S89: Béton et contrats (avec T44) | T89: 5 | U89: Plafond −22, irréversible. Contrainte −4. | V89: Un terminal, un gazoduc, une centrale se décident sur quarante ans. Sécuriser l'approvisionnement d'une région relève de la responsabilité élémentaire d'un État. | W89: Vague de terminaux GNL et de gazoducs lancés avant durcissement réglementaire depuis 2022. | X89: C'est le principal irréversible du camp : ce qui est coulé engage des décennies, quelles que soient les alternances. Le retrait des assureurs et des financeurs est le seul levier qui bloque un projet avant la coulée. | Y89: Pilier · Économique — verrouille 20 à 40 ans d'émissions. Le principal irréversible du camp
A90: T44 | B90: Attentiste | C90: Économique | D90: Contrat d'approvisionnement de long terme | E90: verrouillage contractuel | F90: Mondial | H90: 4 | L90: 2 | N90: 100 | O90: Irréversible | P90: Élevée | Q90: A05 | S90: Béton et contrats (avec T43) · Le carbone déménage (avec T53) | T90: 4 | U90: Plafond −9 sur les trois blocs les plus contraints. Verrouillé par le droit privé. | V90: Un acheteur obtient un prix stable, un vendeur sécurise son investissement. C'est le fonctionnement normal d'un marché de matières premières. | W90: Contrats GNL de vingt à vingt-cinq ans signés en Europe et en Asie depuis 2022. | X90: Le droit privé verrouille ce que la réglementation ne peut plus atteindre : rompre coûte plus cher qu'exécuter. Les contrats GNL de vingt à vingt-cinq ans signés depuis 2022 courent au-delà des objectifs climatiques européens. Une date butoir annoncée très tôt dissuade la signature. | Y90: Noyau · Économique — verrouille par le droit privé ce que la réglementation n'atteint plus
A91: T45 | B91: Attentiste | C91: Économique | D91: Alerte sur l'emploi industriel | E91: chantage à la délocalisation | F91: Bloc | I91: 2 | L91: 1 | N91: 100 | O91: Facile à annuler | P91: Élevée | Q91: A03 | T91: 4 | U91: Friction +15 et contrainte −6. Sans effet si l'ajustement aux frontières protège le bloc. | V91: Un site qui ferme ne rouvre pas, et sa production repart là où la règle est plus souple — sans gain climatique. Le signaler avant la décision est une alerte, pas une menace. | W91: Menaces de fermeture de sites industriels lors de chaque débat sur le prix du carbone. | X91: L'argument est efficace en période électorale et souvent invoqué sans que la fermeture suive. L'ajustement carbone aux frontières supprime l'avantage du moins-disant et donc le fondement de l'alerte. | Y91: Noyau · Économique — convertit une mesure en menace territoriale. Niveau Découverte
A92: T46 | B92: Attentiste | C92: Économique | D92: Cession des actifs sales | E92: nettoyage de bilan | F92: Mondial | H92: 2 | L92: 2 | N92: 100 | O92: Irréversible | P92: Élevée | Q92: A73 | T92: 4 | U92: Perçu +6 partout — le bilan s'améliore vraiment — et contrainte −4 sur les blocs riches. Les émissions, elles, ne bougent pas. | V92: Vendre les actifs les plus émetteurs à des acteurs non cotés fait disparaître les émissions du périmètre déclaré. Elles continuent, hors reporting, souvent avec moins de contraintes qu'avant. | W92: Cessions d'actifs pétroliers et charbonniers des majors vers des sociétés privées non soumises au reporting extra-financier, années 2020. | X92: C'est le seul levier du camp qui améliore le soutien perçu de l'adversaire. Il achète une apparence de progrès au prix d'une perte de contrôle réelle. | Y92: Extension · le bilan se nettoie, les émissions continuent. Très instructif, à réintégrer tôt
A93: T48 | B93: Attentiste | C93: Économique | D93: Retrait public d'un engagement | E93: réalisme assumé | F93: Mondial | H93: 2 | L93: 3 | M93: au moins trois mesures adverses en vigueur — on ne se retire que d'un engagement visible | N93: 100 | O93: Facile à annuler | P93: Élevée | Q93: A15 | S93: La cascade (avec T49) | T93: 4 | U93: Crédibilité du camp actif −10 et perçu −4 partout. Porté à −16 et −6 si une alliance a déjà été quittée. | V93: Abandonner un objectif annoncé coûte peu si un concurrent le fait en même temps : la révision devient du réalisme, et c'est celui qui tient son engagement qui paraît idéologue. | W93: Révisions à la baisse des objectifs renouvelables annoncées par plusieurs majors pétrolières entre 2023 et 2025. | X93: Le retrait est public : il révèle que l'engagement n'était pas contraignant, ce qui affaiblit aussi tous les engagements du même type — y compris ceux du camp attentiste. | Y93: Extension · cascade avec T49 — les deux ensemble ou aucun
A94: T49 | B94: Attentiste | C94: International | D94: Sortie d'une alliance climatique | E94: reprendre sa liberté | F94: Mondial | H94: 3 | L94: 3 | M94: un engagement collectif dont sortir | N94: 78 | O94: Difficile à annuler | P94: Élevée | Q94: A65 | S94: La cascade (avec T48) | T94: 4 | U94: Le mécanisme de révision s'arrête, et la contrainte retombe de 3 sur tous les blocs engagés. | V94: Un engagement collectif ne tient que par le nombre. Le premier départ ne coûte presque rien à celui qui part, et il rend le suivant gratuit. | W94: Départs successifs d'établissements financiers des alliances net zéro sectorielles, 2024-2025. | X94: Il faut un engagement collectif à quitter. Contre un protocole déjà entré en vigueur, la sortie ne défait pas ce qui a été appliqué. | Y94: Extension · cascade avec T48
A95: T50 | B95: Attentiste | C95: Économique | D95: Optimisation des aides publiques | E95: capture de la subvention | F95: Bloc | H95: 2 | L95: 2 | M95: des aides publiques déjà versées | N95: 70 | O95: Difficile à annuler | P95: Moyenne | Q95: A63 | T95: 4 | U95: Contrainte −11 si le bloc a reçu une politique industrielle verte. Sans effet sinon, ni si une institution de suivi existe. | V95: Une aide publique existe pour être utilisée. Une entreprise qui la mobilise dans les règles fait son travail ; c'est au dispositif de fixer ses conditions. | W95: Aides à la transition perçues sans réduction d'émissions vérifiée, dans plusieurs dispositifs nationaux. | X95: Le levier retourne la politique industrielle adverse contre son émetteur : l'argent est encaissé, la trajectoire ne bouge pas. Une institution indépendante de suivi rend l'écart visible dès le rapport suivant. | Y95: Noyau · Économique — PROMU : détourne A19 contre son émetteur. Encaisser l'aide sans changer de trajectoire
A96: T51 | B96: Attentiste | C96: Économique | D96: Neutralité par compensation | E96: compensation au lieu de réduction | F96: Mondial | H96: 1 | L96: 1 | N96: 100 | O96: Facile à annuler | P96: Faible | Q96: A15 | T96: 4 | U96: Perçu −6 partout : l'effort paraît fait alors qu'il ne l'est pas. | V96: Une tonne évitée ailleurs vaut climatiquement une tonne évitée ici, et coûte souvent dix fois moins. Financer la réduction là où elle est la moins chère est rationnel. | W96: Effondrement du marché volontaire du carbone : valeur en baisse de plus de 60 % depuis 2022. | X96: L'équivalence suppose que la réduction ait réellement lieu et soit additionnelle, ce que la majorité des projets examinés ne démontre pas. Le marché volontaire a perdu plus de 60 % de sa valeur depuis 2022. Le reporting obligatoire distingue réduction réelle et crédit acheté. | Y96: Noyau · Économique — achète des crédits au lieu de réduire. Passerelle vers le piège P01
A97: T52 | B97: Attentiste | C97: Économique | D97: Neutralité technologique | E97: exemption technologique | F97: Bloc | H97: 3 | L97: 2 | M97: une norme qui désigne une technologie, à contester au nom de la neutralité | N97: 72 | O97: Difficile à annuler | P97: Élevée | Q97: A04 | T97: 5 | U97: Contrainte −13 et annule un effet différé en attente sur le bloc. | V97: Le législateur fixe l'objectif, pas la solution technique. Interdire une technologie plutôt que des émissions, c'est faire un pari industriel à la place du marché. | W97: Exemption e-fuels obtenue en 2023 sur le règlement européen de fin du thermique en 2035. | X97: L'exemption e-fuels obtenue en 2023 sur le règlement européen de fin du thermique porte sur une filière dont le coût et le rendement restent prohibitifs à l'échelle. Le principe est défendable, son usage ici vide le texte. Sans effet sur un bloc verrouillé. | Y97: Noyau · Économique — inscrit une technologie non viable dans le texte pour en vider l'effet (e-fuels, 2023)
A98: T53 | B98: Attentiste | C98: International | D98: Arbitrage de juridiction | E98: délocalisation | F98: Mondial | H98: 3 | L98: 2 | M98: un bloc contraint à 20 — sans écart de contrainte, il n'y a nulle part où aller | N98: 100 | O98: Irréversible | P98: Élevée | Q98: A03 | S98: Le carbone déménage (avec T44) | T98: 3 | U98: Déplace un dixième des émissions du bloc le plus contraint vers le moins contraint. Le total ne baisse pas — il change d'adresse, et de rythme. Sans effet si le bloc d'arrivée est protégé par l'ajustement aux frontières. | V98: La production intensive en énergie va où la contrainte est la plus faible. Le bloc vertueux voit ses émissions baisser et affiche un résultat ; le monde n'a rien gagné, et il a perdu la contrainte qui s'y appliquait. | W98: Fuite de carbone documentée dans les secteurs intensifs en énergie, argument central des demandes d'exemption à toute tarification nationale. | X98: C'est le seul levier du jeu qui ne détruit aucune mesure : il les contourne. L'ajustement carbone aux frontières est le seul contre, et il doit être posé sur le bloc d'arrivée, pas sur celui de départ. | Y98: Extension · le carbone change d'adresse. Contré par A03, déjà dans le noyau
A99: T60 | B99: Attentiste | C99: Électoral | D99: Référendum sur une mesure climatique | E99: laisser le peuple trancher | F99: Bloc | H99: 3 | J99: 2 | L99: 2 | M99: au moins une mesure adverse en vigueur — un référendum a besoin d'un texte à soumettre | N99: 70 | O99: Irréversible | P99: Élevée | Q99: A60 | S99: La rue et l'urne (avec T61) | U99: Soumet la dernière mesure du bloc au vote, jugé dans deux tours : si le perçu est alors sous 50, elle est annulée ; s'il est au-dessus, le bloc devient protégé. | V99: Un scrutin dédié détache la mesure du bilan d'un gouvernement et la met en concurrence avec le pouvoir d'achat. Le camp qui la défend doit gagner deux fois : l'élection, puis le référendum. | W99: Loi CO₂ suisse rejetée à 51,6 % en juin 2021. Initiatives 732 (2016) et 1631 (2018) sur le prix du carbone dans l'État de Washington, rejetées toutes deux. | X99: Le pari est symétrique : un référendum gagné rend la mesure très difficile à défaire ensuite. Ne se joue pas là où le perçu est déjà haut.
A100: T61 | B100: Attentiste | C100: Électoral | D100: Coalition du coût de la vie | E100: front du pouvoir d'achat | F100: Bloc | H100: 2 | L100: 1 | N100: 100 | O100: Facile à annuler | P100: Moyenne | Q100: A31 | S100: La rue et l'urne (avec T60) | U100: Friction +16 et perçu −7. Effet réduit de moitié si la redistribution est installée sur le bloc. | V100: Rassembler sous un même mot d'ordre des intérêts qui n'ont rien en commun sauf de payer la mesure : automobilistes, artisans, agriculteurs, ménages chauffés au fioul. | W100: Gilets jaunes, novembre 2018 : la taxe carbone française est gelée en trois semaines. Campagne « Axe the Tax » australienne, 2013-2014. | X100: La coalition se défait dès que la compensation devient visible et datée : c'est le seul contre-feu qui marche.
...

Sheet Non retenus
A1: ID catalogue | B1: Camp | C1: Famille | D1: Levier | E1: Puissance réelle | F1: Verdict août 2026 | G1: Motif d'août | H1: Verdict v0.9.1 | I1: Pourquoi | J1: Ancrage réel daté
A2: A06 | B2: Actif | C2: Réglementaire | D2: Norme bâtiment / interdiction des passoires | E2: 3 | F2: À tester | G2: Extension · à garder si la friction propriétaire est modélisée (absorbe A09) | H2: Écarté — pas de décision distincte | I2: Défendable, mais n'ouvre aucun choix que le jeu ne propose autrement. | J2: Calendrier DPE FR : classe G en 2025, F en 2028
A3: A08 | B3: Actif | C3: Réglementaire | D3: Plafond d'émission des centrales | E3: 4 | F3: À tester | G3: Extension · recouvre partiellement A02 et A05 — vérifier qu'il apporte une décision distincte | H3: Écarté — redondance | I3: Le jeu produit déjà la même décision par une autre carte. | J3: Clean Power Plan US 2015, annulé en 2019 puis remplacé — exemple d'annulabilité
A4: A09 | B4: Actif | C4: Réglementaire | D4: Obligation de rénovation énergétique | E4: 3 | F4: Écarté | G4: Fusionné dans A06 (norme bâtiment) — même effet, même friction, deux cartes redondantes | H4: Écarté — fusionné en août | I4: Fusion décidée le 17 août 2026 et maintenue : voir le motif d'origine. | J4: Directive UE performance énergétique des bâtiments, révisée 2024
A5: A13 | B5: Actif | C5: Réglementaire | D5: Zone à faibles émissions | E5: 2 | F5: À tester | G5: Extension · portée locale : n'existe mécaniquement que si le jeu descend sous le bloc | H5: Écarté — hors échelle | I5: Portée locale : n'existe mécaniquement que si le jeu descend sous le bloc, ce qu'il ne fait pas. | J5: ZFE françaises ; ULEZ Londres 2023 et son coût électoral
A6: A14 | B6: Actif | C6: Réglementaire | D6: Planification urbaine et fin de l'étalement | E6: 4 | F6: À tester | G6: Extension · horizon trop long pour 8 à 20 tours — chercher une représentation lisible | H6: Écarté — pas de décision distincte | I6: Défendable, mais n'ouvre aucun choix que le jeu ne propose autrement. | J6: Objectif ZAN français ; politiques de densification
A7: A16 | B7: Actif | C7: Réglementaire | D7: Devoir de vigilance sur la chaîne de valeur | E7: 3 | F7: Écarté | G7: Fusionné dans A15 (reporting) — même famille, même contre-levier T20 | H7: Écarté — fusionné en août | I7: Fusion décidée le 17 août 2026 et maintenue : voir le motif d'origine. | J7: Loi FR 2017 ; directive CSDDD UE 2024, périmètre réduit en 2025
A8: A23 | B8: Actif | C8: Économique | D8: Verdissement de la banque centrale | E8: 3 | F8: À tester | G8: Extension · technocratique, hors du champ électoral : tester si le joueur comprend l'effet | H8: Écarté — pas de décision distincte | I8: Défendable, mais n'ouvre aucun choix que le jeu ne propose autrement. | J8: Verdissement du portefeuille d'obligations d'entreprises de la BCE, 2022
A9: A24 | B9: Actif | C9: Économique | D9: Exigences prudentielles et stress tests climat | E9: 3 | F9: Écarté | G9: Fusionné dans A23 (banque centrale) — encore moins lisible pour le joueur | H9: Écarté — fusionné en août | I9: Fusion décidée le 17 août 2026 et maintenue : voir le motif d'origine. | J9: Stress tests climatiques BCE 2022 ; travaux du NGFS
A10: A30 | B10: Actif | C10: Économique | D10: Partenariat de transition juste (JETP) | E10: 2 | F10: Écarté | G10: Fusionné dans A29 (financement Nord-Sud) — décaissements réels trop faibles pour justifier une carte propre | H10: Écarté — fusionné en août | I10: Fusion décidée le 17 août 2026 et maintenue : voir le motif d'origine. | J10: JETP Afrique du Sud 2021, Indonésie et Vietnam 2022 : décaissements lents
A11: A32 | B11: Actif | C11: Économique | D11: Commande publique verte | E11: 3 | F11: À tester | G11: Extension · 10 à 15 % du PIB, très peu exploité dans le réel : gisement de jeu, effet difficile à chiffrer | H11: Écarté — pas de décision distincte | I11: Défendable, mais n'ouvre aucun choix que le jeu ne propose autrement. | J11: Buy Clean californien ; clauses carbone des marchés publics UE
A12: A34 | B12: Actif | C12: Judiciaire | D12: Contentieux contre une entreprise | E12: 3 | F12: À tester | G12: Extension · gain infirmé en appel (Shell, 2024) — modéliser la fragilité plutôt que le gain | H12: Écarté — redondance | I12: Le jeu produit déjà la même décision par une autre carte. | J12: Milieudefensie c. Shell : -45 % ordonné en 2021, infirmé en appel en 2024
A13: A42 | B13: Actif | C13: Technologique | D13: Efficacité matière et économie circulaire | E13: 3 | F13: À tester | G13: Extension · angle mort réel des politiques, difficile à modéliser | H13: Non construit — identifiant occupé | I13: Efficacité matière et économie circulaire : non construit, et l'identifiant A42 désigne un piège dans le jeu. | J13: Travaux du Shift Project sur l'industrie ; référentiels ADEME
... A35: T47 | B35: Attentiste | C35: Économique | D35: Rachat d'actions plutôt qu'investissement | E35: 3 | F35: À tester | G35: Extension · retire du capital du jeu plutôt que de le transformer | H35: Écarté — redondance | I35: Le jeu produit déjà la même décision par une autre carte. | J35: Records de rachats d'actions des majors pétrolières en 2022-2023

Sheet Correspondance
A1: ID catalogue | B1: ID dans le jeu | C1: Levier | D1: Pourquoi l'identifiant a changé
A2: P01 | B2: A22 | C2: Compensation carbone volontaire | D2: Piège renuméroté dans la série A en v0.5 : un identifiant commençant par P annonçait le piège au joueur.
A3: P04 | B3: A42 | C3: Hydrogène pour la voiture particulière | D3: idem
A4: P05 | B4: A43 | C4: Carburants de synthèse pour l'automobile | D4: idem
A5: P07 | B5: A38 | C5: Captage et stockage sur centrale électrique | D5: idem
A6: P08 | B6: A09 | C6: Objectif net zéro 2050 | D6: idem
A7: P10 | B7: A26 | C7: Programme nucléaire accéléré | D7: idem
A8: A38 | B8: A70 | C8: Contentieux en responsabilité fondé sur l'attribution | D8: Intégré en v0.9 ; l'identifiant A38 était déjà pris par le piège ex-P07.
A9: A22 | B9: A73 | C9: Fin du financement public à l'export des fossiles | D9: Intégré en v0.9.1 ; l'identifiant A22 était déjà pris par le piège ex-P01.
A10: P09 | B10: T68 | C10: Géo-ingénierie solaire à l'étude | D10: Écrit en v0.7 comme levier attentiste plutôt que comme piège.
A11: T14 | B11: T62 | C11: Financement de campagne | D11: Recouvert par T62, écrit en v0.7 : même ancrage, mécanique plus nette.
A12: A26 | B12: — | C12: Actionnariat actif et résolutions climat | D12: Devenu un événement du jeu en v0.9 : non reproductible à volonté.
... A14: P11 | B14: — | C14: Sommet international sans mécanisme contraignant | D14: Était déjà un événement du jeu depuis l'origine (Sommet international).
A16: Six identifiants de la série A désignent, dans le jeu, un piège différent du levier qu'ils nomment dans le catalogue d'août. Toute lecture croisée des deux fichiers doit passer par cette table.

Sheet Contrôles
A1: Contrôles du catalogue
A2: Colonne B : formule, recalculée à l'ouverture du fichier. Colonne C : la même valeur au moment de la génération.
A3: Les deux colonnes doivent coïncider. Un écart signale que le catalogue a été édité à la main depuis sa génération.
A5: Répartition par camp
A7: Actif | B7: =COUNTIF(Catalogue!$B$2:$B$113,"Actif") | C7: 57
A8: Attentiste | B8: =COUNTIF(Catalogue!$B$2:$B$113,"Attentiste") | C8: 55
A9: dont pièges | B9: =COUNTIF(Catalogue!$R$2:$R$113,"oui") | C9: 8
A10: Total des leviers | B10: =COUNTA(Catalogue!$A$2:$A$113) | C10: 112
A12: Répartition par famille
A14: Discours — Attentiste | B14: =COUNTIFS(Catalogue!$C$2:$C$113,"Discours",Catalogue!$B$2:$B$113,"Attentiste") | C14: 8
A15: Institutionnel — Attentiste | B15: =COUNTIFS(Catalogue!$C$2:$C$113,"Institutionnel",Catalogue!$B$2:$B$113,"Attentiste") | C15: 7
A16: International — Actif | B16: =COUNTIFS(Catalogue!$C$2:$C$113,"International",Catalogue!$B$2:$B$113,"Actif") | C16: 5
A17: International — Attentiste | B17: =COUNTIFS(Catalogue!$C$2:$C$113,"International",Catalogue!$B$2:$B$113,"Attentiste") | C17: 6
A18: Judiciaire — Actif | B18: =COUNTIFS(Catalogue!$C$2:$C$113,"Judiciaire",Catalogue!$B$2:$B$113,"Actif") | C18: 5
A19: Judiciaire — Attentiste | B19: =COUNTIFS(Catalogue!$C$2:$C$113,"Judiciaire",Catalogue!$B$2:$B$113,"Attentiste") | C19: 5
A20: Narratif — Actif | B20: =COUNTIFS(Catalogue!$C$2:$C$113,"Narratif",Catalogue!$B$2:$B$113,"Actif") | C20: 8
A21: Narratif — Attentiste | B21: =COUNTIFS(Catalogue!$C$2:$C$113,"Narratif",Catalogue!$B$2:$B$113,"Attentiste") | C21: 8
A22: Réglementaire — Actif | B22: =COUNTIFS(Catalogue!$C$2:$C$113,"Réglementaire",Catalogue!$B$2:$B$113,"Actif") | C22: 13
A23: Réglementaire — Attentiste | B23: =COUNTIFS(Catalogue!$C$2:$C$113,"Réglementaire",Catalogue!$B$2:$B$113,"Attentiste") | C23: 3
A24: Technologique — Actif | B24: =COUNTIFS(Catalogue!$C$2:$C$113,"Technologique",Catalogue!$B$2:$B$113,"Actif") | C24: 10
A25: Technologique — Attentiste | B25: =COUNTIFS(Catalogue!$C$2:$C$113,"Technologique",Catalogue!$B$2:$B$113,"Attentiste") | C25: 4
A26: Économique — Actif | B26: =COUNTIFS(Catalogue!$C$2:$C$113,"Économique",Catalogue!$B$2:$B$113,"Actif") | C26: 10
A27: Économique — Attentiste | B27: =COUNTIFS(Catalogue!$C$2:$C$113,"Économique",Catalogue!$B$2:$B$113,"Attentiste") | C27: 10
A28: Électoral — Actif | B28: =COUNTIFS(Catalogue!$C$2:$C$113,"Électoral",Catalogue!$B$2:$B$113,"Actif") | C28: 6
A29: Électoral — Attentiste | B29: =COUNTIFS(Catalogue!$C$2:$C$113,"Électoral",Catalogue!$B$2:$B$113,"Attentiste") | C29: 4
A31: Ouverture par époque
A33: Époque 1 — à partir de 2015 | B33: =COUNTIF(Catalogue!$L$2:$L$113,1) | C33: 49
A34: Époque 2 — à partir de 2035 | B34: =COUNTIF(Catalogue!$L$2:$L$113,2) | C34: 39
A35: Époque 3 — à partir de 2055 | B35: =COUNTIF(Catalogue!$L$2:$L$113,3) | C35: 24
A37: Cohérence des contre-leviers
A39: Leviers sans contre-levier désigné | B39: =COUNTBLANK(Catalogue!$Q$2:$Q$113) | C39: 2 | D39: Sans contre : A71, T38
A40: Contre-leviers pointant hors du jeu | B40: 0 | C40: 0 | D40: Orphelins : aucun — vérifié en Python, aucune formule ne peut le faire.
A42: Puissance réelle (colonne à remplir)
A44: Leviers dont la puissance a été estimée en août | B44: =COUNT(Catalogue!$T$2:$T$113) | C44: 97
A45: Leviers sans estimation (cellules jaunes) | B45: =112-COUNT(Catalogue!$T$2:$T$113) | C45: 15
A46: Puissance moyenne — Actif | B46: =ROUND(AVERAGEIFS(Catalogue!$T$2:$T$113,Catalogue!$B$2:$B$113,"Actif"),2) | C46: 3.27 | D46: L'asymétrie du catalogue d'août est-elle conservée ?
A47: Puissance moyenne — Attentiste | B47: =ROUND(AVERAGEIFS(Catalogue!$T$2:$T$113,Catalogue!$B$2:$B$113,"Attentiste"),2) | C47: 4.14
A49: Leviers du catalogue jamais construits
A51: Total | B51: =COUNTA('Non retenus'!$A$2:$A$200) | C51: 34 | D51: Chacun porte un verdict dans l'onglet Non retenus : aucun n'est laissé en suspens.
